[{"temp":{"units":"C","value":10.49},"sunrise":{"value":"2020-10-03T05:26:20.312Z"},"observation_time":{"value":"2020-10-03T12:00:00.000Z"},"dewpoint":{"units":"C","value":7.61},"precipitation_type":{"value":"rain"},"lon":9.183333,"surface_shortwave_radiation":{"units":"w/sqm","value":9.33},"wind_gust":{"units":"m/s","value":8.58},"precipitation":{"units":"mm/hr","value":1.9595},"precipitation_probability":{"units":"%","value":35},"sunset":{"value":"2020-10-03T16:57:42.083Z"},"cloud_cover":{"units":"%","value":100},"humidity":{"units":"%","value":82.46},"wind_speed":{"units":"m/s","value":2.75},"lat":48.783333},{"temp":{"units":"C","value":11.84},"sunrise":{"value":"2020-10-03T05:26:20.312Z"},"observation_time":{"value":"2020-10-03T13:00:00.000Z"},"dewpoint":{"units":"C","value":7.74},"precipitation_type":{"value":"rain"},"lon":9.183333,"surface_shortwave_radiation":{"units":"w/sqm","value":8.91},"wind_gust":{"units":"m/s","value":6.14},"precipitation":{"units":"mm/hr","value":0.0293},"precipitation_probability":{"units":"%","value":30},"sunset":{"value":"2020-10-03T16:57:42.083Z"},"cloud_cover":{"units":"%","value":98.63},"humidity":{"units":"%","value":75.71},"wind_speed":{"units":"m/s","value":1.99},"lat":48.783333},{"temp":{"units":"C","value":13.46},"sunrise":{"value":"2020-10-03T05:26:20.312Z"},"observation_time":{"value":"2020-10-03T14:00:00.000Z"},"dewpoint":{"units":"C","value":8.13},"precipitation_type":{"value":"none"},"lon":9.183333,"surface_shortwave_radiation":{"units":"w/sqm","value":29.42},"wind_gust":{"units":"m/s","value":5.61},"precipitation":{"units":"mm/hr","value":0},"precipitation_probability":{"units":"%","value":20},"sunset":{"value":"2020-10-03T16:57:42.083Z"},"cloud_cover":{"units":"%","value":60.36},"humidity":{"units":"%","value":69.6},"wind_speed":{"units":"m/s","value":2.28},"lat":48.783333},{"temp":{"units":"C","value":14.11},"sunrise":{"value":"2020-10-03T05:26:20.312Z"},"observation_time":{"value":"2020-10-03T15:00:00.000Z"},"dewpoint":{"units":"C","value":7.93},"precipitation_type":{"value":"none"},"lon":9.183333,"surface_shortwave_radiation":{"units":"w/sqm","value":48.75},"wind_gust":{"units":"m/s","value":6.49},"precipitation":{"units":"mm/hr","value":0},"precipitation_probability":{"units":"%","value":5},"sunset":{"value":"2020-10-03T16:57:42.083Z"},"cloud_cover":{"units":"%","value":31.48},"humidity":{"units":"%","value":65.27},"wind_speed":{"units":"m/s","value":2.18},"lat":48.783333},{"temp":{"units":"C","value":13.28},"sunrise":{"value":"2020-10-03T05:26:20.312Z"},"observation_time":{"value":"2020-10-03T16:00:00.000Z"},"dewpoint":{"units":"C","value":9.03},"precipitation_type":{"value":"none"},"lon":9.183333,"surface_shortwave_radiation":{"units":"w/sqm","value":53.14},"wind_gust":{"units":"m/s","value":5.75},"precipitation":{"units":"mm/hr","value":0},"precipitation_probability":{"units":"%","value":0},"sunset":{"value":"2020-10-03T16:57:42.083Z"},"cloud_cover":{"units":"%","value":12.03},"humidity":{"units":"%","value":74.34},"wind_speed":{"units":"m/s","value":2.46},"lat":48.783333},{"temp":{"units":"C","value":11.68},"sunrise":{"value":"2020-10-03T05:26:20.312Z"},"observation_time":{"value":"2020-10-03T17:00:00.000Z"},"dewpoint":{"units":"C","value":8.6},"precipitation_type":{"value":"none"},"lon":9.183333,"surface_shortwave_radiation":{"units":"w/sqm","value":49.41},"wind_gust":{"units":"m/s","value":5.81},"precipitation":{"units":"mm/hr","value":0},"precipitation_probability":{"units":"%","value":0},"sunset":{"value":"2020-10-03T16:57:42.083Z"},"cloud_cover":{"units":"%","value":1.76},"humidity":{"units":"%","value":80.84},"wind_speed":{"units":"m/s","value":1.62},"lat":48.783333},{"temp":{"units":"C","value":10.62},"sunrise":{"value":"2020-10-03T05:26:20.312Z"},"observation_time":{"value":"2020-10-03T18:00:00.000Z"},"dewpoint":{"units":"C","value":7.98},"precipitation_type":{"value":"none"},"lon":9.183333,"surface_shortwave_radiation":{"units":"w/sqm","value":45.29},"wind_gust":{"units":"m/s","value":3.56},"precipitation":{"units":"mm/hr","value":0},"precipitation_probability":{"units":"%","value":0},"sunset":{"value":"2020-10-03T16:57:42.083Z"},"cloud_cover":{"units":"%","value":7.51},"humidity":{"units":"%","value":81.93},"wind_speed":{"units":"m/s","value":1.26},"lat":48.783333},{"temp":{"units":"C","value":9.9},"sunrise":{"value":"2020-10-03T05:26:20.312Z"},"observation_time":{"value":"2020-10-03T19:00:00.000Z"},"dewpoint":{"units":"C","value":7.78},"precipitation_type":{"value":"none"},"lon":9.183333,"surface_shortwave_radiation":{"units":"w/sqm","value":41.8},"wind_gust":{"units":"m/s","value":3.27},"precipitation":{"units":"mm/hr","value":0},"precipitation_probability":{"units":"%","value":0},"sunset":{"value":"2020-10-03T16:57:42.083Z"},"cloud_cover":{"units":"%","value":38.07},"humidity":{"units":"%","value":84.56},"wind_speed":{"units":"m/s","value":1.16},"lat":48.783333},{"temp":{"units":"C","value":9.54},"sunrise":{"value":"2020-10-03T05:26:20.312Z"},"observation_time":{"value":"2020-10-03T20:00:00.000Z"},"dewpoint":{"units":"C","value":7.57},"precipitation_type":{"value":"none"},"lon":9.183333,"surface_shortwave_radiation":{"units":"w/sqm","value":38.82},"wind_gust":{"units":"m/s","value":3.27},"precipitation":{"units":"mm/hr","value":0},"precipitation_probability":{"units":"%","value":0},"sunset":{"value":"2020-10-03T16:57:42.083Z"},"cloud_cover":{"units":"%","value":45.77},"humidity":{"units":"%","value":86.84},"wind_speed":{"units":"m/s","value":1.49},"lat":48.783333},{"temp":{"units":"C","value":9.36},"sunrise":{"value":"2020-10-03T05:26:20.312Z"},"observation_time":{"value":"2020-10-03T21:00:00.000Z"},"dewpoint":{"units":"C","value":6.95},"precipitation_type":{"value":"none"},"lon":9.183333,"surface_shortwave_radiation":{"units":"w/sqm","value":49.47},"wind_gust":{"units":"m/s","value":4.03},"precipitation":{"units":"mm/hr","value":0},"precipitation_probability":{"units":"%","value":5},"sunset":{"value":"2020-10-03T16:57:42.083Z"},"cloud_cover":{"units":"%","value":99.08},"humidity":{"units":"%","value":84.66},"wind_speed":{"units":"m/s","value":1.76},"lat":48.783333},{"temp":{"units":"C","value":9.27},"sunrise":{"value":"2020-10-03T05:26:20.312Z"},"observation_time":{"value":"2020-10-03T22:00:00.000Z"},"dewpoint":{"units":"C","value":6.49},"precipitation_type":{"value":"none"},"lon":9.183333,"surface_shortwave_radiation":{"units":"w/sqm","value":45.66},"wind_gust":{"units":"m/s","value":3.86},"precipitation":{"units":"mm/hr","value":0},"precipitation_probability":{"units":"%","value":5},"sunset":{"value":"2020-10-03T16:57:42.083Z"},"cloud_cover":{"units":"%","value":98.65},"humidity":{"units":"%","value":81.75},"wind_speed":{"units":"m/s","value":1.56},"lat":48.783333},{"temp":{"units":"C","value":9.06},"sunrise":{"value":"2020-10-03T05:26:20.312Z"},"observation_time":{"value":"2020-10-03T23:00:00.000Z"},"dewpoint":{"units":"C","value":6.31},"precipitation_type":{"value":"none"},"lon":9.183333,"surface_shortwave_radiation":{"units":"w/sqm","value":42.4},"wind_gust":{"units":"m/s","value":3.37},"precipitation":{"units":"mm/hr","value":0},"precipitation_probability":{"units":"%","value":10},"sunset":{"value":"2020-10-03T16:57:42.083Z"},"cloud_cover":{"units":"%","value":100},"humidity":{"units":"%","value":82.24},"wind_speed":{"units":"m/s","value":1.18},"lat":48.783333},{"temp":{"units":"C","value":9.01},"sunrise":{"value":"2020-10-04T05:27:48.253Z"},"observation_time":{"value":"2020-10-04T00:00:00.000Z"},"dewpoint":{"units":"C","value":6.08},"precipitation_type":{"value":"none"},"lon":9.183333,"surface_shortwave_radiation":{"units":"w/sqm","value":39.57},"wind_gust":{"units":"m/s","value":3.38},"precipitation":{"units":"mm/hr","value":0},"precipitation_probability":{"units":"%","value":20},"sunset":{"value":"2020-10-04T16:55:37.456Z"},"cloud_cover":{"units":"%","value":89.97},"humidity":{"units":"%","value":81.22},"wind_speed":{"units":"m/s","value":1.44},"lat":48.783333},{"temp":{"units":"C","value":8.98},"sunrise":{"value":"2020-10-04T05:27:48.253Z"},"observation_time":{"value":"2020-10-04T01:00:00.000Z"},"dewpoint":{"units":"C","value":6.21},"precipitation_type":{"value":"rain"},"lon":9.183333,"surface_shortwave_radiation":{"units":"w/sqm","value":28.6},"wind_gust":{"units":"m/s","value":3.89},"precipitation":{"units":"mm/hr","value":0.1113},"precipitation_probability":{"units":"%","value":30},"sunset":{"value":"2020-10-04T16:55:37.456Z"},"cloud_cover":{"units":"%","value":93.52},"humidity":{"units":"%","value":83.79},"wind_speed":{"units":"m/s","value":1.78},"lat":48.783333},{"temp":{"units":"C","value":9.8},"sunrise":{"value":"2020-10-04T05:27:48.253Z"},"observation_time":{"value":"2020-10-04T02:00:00.000Z"},"dewpoint":{"units":"C","value":6.49},"precipitation_type":{"value":"rain"},"lon":9.183333,"surface_shortwave_radiation":{"units":"w/sqm","value":27.17},"wind_gust":{"units":"m/s","value":5.1},"precipitation":{"units":"mm/hr","value":0.6992},"precipitation_probability":{"units":"%","value":35},"sunset":{"value":"2020-10-04T16:55:37.456Z"},"cloud_cover":{"units":"%","value":88.33},"humidity":{"units":"%","value":79.86},"wind_speed":{"units":"m/s","value":2.22},"lat":48.783333},{"temp":{"units":"C","value":10.99},"sunrise":{"value":"2020-10-04T05:27:48.253Z"},"observation_time":{"value":"2020-10-04T03:00:00.000Z"},"dewpoint":{"units":"C","value":5.29},"precipitation_type":{"value":"none"},"lon":9.183333,"surface_shortwave_radiation":{"units":"w/sqm","value":25.88},"wind_gust":{"units":"m/s","value":11.83},"precipitation":{"units":"mm/hr","value":0},"precipitation_probability":{"units":"%","value":30},"sunset":{"value":"2020-10-04T16:55:37.456Z"},"cloud_cover":{"units":"%","value":45.59},"humidity":{"units":"%","value":67.36},"wind_speed":{"units":"m/s","value":5.34},"lat":48.783333},{"temp":{"units":"C","value":11.01},"sunrise":{"value":"2020-10-04T05:27:48.253Z"},"observation_time":{"value":"2020-10-04T04:00:00.000Z"},"dewpoint":{"units":"C","value":5.04},"precipitation_type":{"value":"none"},"lon":9.183333,"surface_shortwave_radiation":{"units":"w/sqm","value":24.7},"wind_gust":{"units":"m/s","value":13.26},"precipitation":{"units":"mm/hr","value":0},"precipitation_probability":{"units":"%","value":15},"sunset":{"value":"2020-10-04T16:55:37.456Z"},"cloud_cover":{"units":"%","value":100},"humidity":{"units":"%","value":66.35},"wind_speed":{"units":"m/s","value":5.02},"lat":48.783333},{"temp":{"units":"C","value":11.03},"sunrise":{"value":"2020-10-04T05:27:48.253Z"},"observation_time":{"value":"2020-10-04T05:00:00.000Z"},"dewpoint":{"units":"C","value":4.86},"precipitation_type":{"value":"none"},"lon":9.183333,"surface_shortwave_radiation":{"units":"w/sqm","value":23.63},"wind_gust":{"units":"m/s","value":11.84},"precipitation":{"units":"mm/hr","value":0},"precipitation_probability":{"units":"%","value":10},"sunset":{"value":"2020-10-04T16:55:37.456Z"},"cloud_cover":{"units":"%","value":100},"humidity":{"units":"%","value":65.08},"wind_speed":{"units":"m/s","value":5.23},"lat":48.783333},{"temp":{"units":"C","value":11.12},"sunrise":{"value":"2020-10-04T05:27:48.253Z"},"observation_time":{"value":"2020-10-04T06:00:00.000Z"},"dewpoint":{"units":"C","value":4.81},"precipitation_type":{"value":"none"},"lon":9.183333,"surface_shortwave_radiation":{"units":"w/sqm","value":22.65},"wind_gust":{"units":"m/s","value":14.51},"precipitation":{"units":"mm/hr","value":0},"precipitation_probability":{"units":"%","value":10},"sunset":{"value":"2020-10-04T16:55:37.456Z"},"cloud_cover":{"units":"%","value":100},"humidity":{"units":"%","value":64.57},"wind_speed":{"units":"m/s","value":6.49},"lat":48.783333},{"temp":{"units":"C","value":11.23},"sunrise":{"value":"2020-10-04T05:27:48.253Z"},"observation_time":{"value":"2020-10-04T07:00:00.000Z"},"dewpoint":{"units":"C","value":4.52},"precipitation_type":{"value":"none"},"lon":9.183333,"surface_shortwave_radiation":{"units":"w/sqm","value":22.07},"wind_gust":{"units":"m/s","value":14.97},"precipitation":{"units":"mm/hr","value":0},"precipitation_probability":{"units":"%","value":5},"sunset":{"value":"2020-10-04T16:55:37.456Z"},"cloud_cover":{"units":"%","value":92.5},"humidity":{"units":"%","value":62.84},"wind_speed":{"units":"m/s","value":5.31},"lat":48.783333},{"temp":{"units":"C","value":12.17},"sunrise":{"value":"2020-10-04T05:27:48.253Z"},"observation_time":{"value":"2020-10-04T08:00:00.000Z"},"dewpoint":{"units":"C","value":4.69},"precipitation_type":{"value":"none"},"lon":9.183333,"surface_shortwave_radiation":{"units":"w/sqm","value":22.84},"wind_gust":{"units":"m/s","value":12.57},"precipitation":{"units":"mm/hr","value":0},"precipitation_probability":{"units":"%","value":0},"sunset":{"value":"2020-10-04T16:55:37.456Z"},"cloud_cover":{"units":"%","value":83.63},"humidity":{"units":"%","value":59.66},"wind_speed":{"units":"m/s","value":5.58},"lat":48.783333},{"temp":{"units":"C","value":13.51},"sunrise":{"value":"2020-10-04T05:27:48.253Z"},"observation_time":{"value":"2020-10-04T09:00:00.000Z"},"dewpoint":{"units":"C","value":4.14},"precipitation_type":{"value":"none"},"lon":9.183333,"surface_shortwave_radiation":{"units":"w/sqm","value":30.3},"wind_gust":{"units":"m/s","value":12.73},"precipitation":{"units":"mm/hr","value":0},"precipitation_probability":{"units":"%","value":0},"sunset":{"value":"2020-10-04T16:55:37.456Z"},"cloud_cover":{"units":"%","value":30.14},"humidity":{"units":"%","value":52.67},"wind_speed":{"units":"m/s","value":5.61},"lat":48.783333},{"temp":{"units":"C","value":14.33},"sunrise":{"value":"2020-10-04T05:27:48.253Z"},"observation_time":{"value":"2020-10-04T10:00:00.000Z"},"dewpoint":{"units":"C","value":3.77},"precipitation_type":{"value":"none"},"lon":9.183333,"surface_shortwave_radiation":{"units":"w/sqm","value":43.5},"wind_gust":{"units":"m/s","value":13.02},"precipitation":{"units":"mm/hr","value":0},"precipitation_probability":{"units":"%","value":0},"sunset":{"value":"2020-10-04T16:55:37.456Z"},"cloud_cover":{"units":"%","value":20.78},"humidity":{"units":"%","value":48.45},"wind_speed":{"units":"m/s","value":5.55},"lat":48.783333},{"temp":{"units":"C","value":15.08},"sunrise":{"value":"2020-10-04T05:27:48.253Z"},"observation_time":{"value":"2020-10-04T11:00:00.000Z"},"dewpoint":{"units":"C","value":3.2},"precipitation_type":{"value":"none"},"lon":9.183333,"surface_shortwave_radiation":{"units":"w/sqm","value":57.82},"wind_gust":{"units":"m/s","value":13.16},"precipitation":{"units":"mm/hr","value":0},"precipitation_probability":{"units":"%","value":0},"sunset":{"value":"2020-10-04T16:55:37.456Z"},"cloud_cover":{"units":"%","value":31.81},"humidity":{"units":"%","value":44.33},"wind_speed":{"units":"m/s","value":5.73},"lat":48.783333},{"temp":{"units":"C","value":15.99},"sunrise":{"value":"2020-10-04T05:27:48.253Z"},"observation_time":{"value":"2020-10-04T12:00:00.000Z"},"dewpoint":{"units":"C","value":2.54},"precipitation_type":{"value":"none"},"lon":9.183333,"surface_shortwave_radiation":{"units":"w/sqm","value":70.66},"wind_gust":{"units":"m/s","value":13.03},"precipitation":{"units":"mm/hr","value":0},"precipitation_probability":{"units":"%","value":0},"sunset":{"value":"2020-10-04T16:55:37.456Z"},"cloud_cover":{"units":"%","value":19.78},"humidity":{"units":"%","value":40.25},"wind_speed":{"units":"m/s","value":4.92},"lat":48.783333},{"temp":{"units":"C","value":16.46},"sunrise":{"value":"2020-10-04T05:27:48.253Z"},"observation_time":{"value":"2020-10-04T13:00:00.000Z"},"dewpoint":{"units":"C","value":3.6},"precipitation_type":{"value":"none"},"lon":9.183333,"surface_shortwave_radiation":{"units":"w/sqm","value":82.3},"wind_gust":{"units":"m/s","value":11.62},"precipitation":{"units":"mm/hr","value":0},"precipitation_probability":{"units":"%","value":0},"sunset":{"value":"2020-10-04T16:55:37.456Z"},"cloud_cover":{"units":"%","value":21.12},"humidity":{"units":"%","value":41.43},"wind_speed":{"units":"m/s","value":3.74},"lat":48.783333},{"temp":{"units":"C","value":16.66},"sunrise":{"value":"2020-10-04T05:27:48.253Z"},"observation_time":{"value":"2020-10-04T14:00:00.000Z"},"dewpoint":{"units":"C","value":4.52},"precipitation_type":{"value":"none"},"lon":9.183333,"surface_shortwave_radiation":{"units":"w/sqm","value":90.43},"wind_gust":{"units":"m/s","value":8.71},"precipitation":{"units":"mm/hr","value":0},"precipitation_probability":{"units":"%","value":0},"sunset":{"value":"2020-10-04T16:55:37.456Z"},"cloud_cover":{"units":"%","value":58.18},"humidity":{"units":"%","value":44.55},"wind_speed":{"units":"m/s","value":2.41},"lat":48.783333},{"temp":{"units":"C","value":16.31},"sunrise":{"value":"2020-10-04T05:27:48.253Z"},"observation_time":{"value":"2020-10-04T15:00:00.000Z"},"dewpoint":{"units":"C","value":5.31},"precipitation_type":{"value":"none"},"lon":9.183333,"surface_shortwave_radiation":{"units":"w/sqm","value":91.46},"wind_gust":{"units":"m/s","value":7.86},"precipitation":{"units":"mm/hr","value":0},"precipitation_probability":{"units":"%","value":0},"sunset":{"value":"2020-10-04T16:55:37.456Z"},"cloud_cover":{"units":"%","value":100},"humidity":{"units":"%","value":46.91},"wind_speed":{"units":"m/s","value":2.48},"lat":48.783333},{"temp":{"units":"C","value":15.44},"sunrise":{"value":"2020-10-04T05:27:48.253Z"},"observation_time":{"value":"2020-10-04T16:00:00.000Z"},"dewpoint":{"units":"C","value":5.93},"precipitation_type":{"value":"none"},"lon":9.183333,"surface_shortwave_radiation":{"units":"w/sqm","value":88.91},"wind_gust":{"units":"m/s","value":5.72},"precipitation":{"units":"mm/hr","value":0},"precipitation_probability":{"units":"%","value":5},"sunset":{"value":"2020-10-04T16:55:37.456Z"},"cloud_cover":{"units":"%","value":100},"humidity":{"units":"%","value":52.29},"wind_speed":{"units":"m/s","value":2.13},"lat":48.783333},{"temp":{"units":"C","value":14.21},"sunrise":{"value":"2020-10-04T05:27:48.253Z"},"observation_time":{"value":"2020-10-04T17:00:00.000Z"},"dewpoint":{"units":"C","value":6.11},"precipitation_type":{"value":"none"},"lon":9.183333,"surface_shortwave_radiation":{"units":"w/sqm","value":86.37},"wind_gust":{"units":"m/s","value":4.33},"precipitation":{"units":"mm/hr","value":0},"precipitation_probability":{"units":"%","value":5},"sunset":{"value":"2020-10-04T16:55:37.456Z"},"cloud_cover":{"units":"%","value":92.8},"humidity":{"units":"%","value":57.04},"wind_speed":{"units":"m/s","value":1.12},"lat":48.783333},{"temp":{"units":"C","value":13.26},"sunrise":{"value":"2020-10-04T05:27:48.253Z"},"observation_time":{"value":"2020-10-04T18:00:00.000Z"},"dewpoint":{"units":"C","value":6.64},"precipitation_type":{"value":"none"},"lon":9.183333,"surface_shortwave_radiation":{"units":"w/sqm","value":83.97},"wind_gust":{"units":"m/s","value":2.48},"precipitation":{"units":"mm/hr","value":0},"precipitation_probability":{"units":"%","value":5},"sunset":{"value":"2020-10-04T16:55:37.456Z"},"cloud_cover":{"units":"%","value":90.42},"humidity":{"units":"%","value":63.29},"wind_speed":{"units":"m/s","value":0.9},"lat":48.783333},{"temp":{"units":"C","value":12.6},"sunrise":{"value":"2020-10-04T05:27:48.253Z"},"observation_time":{"value":"2020-10-04T19:00:00.000Z"},"dewpoint":{"units":"C","value":7.12},"precipitation_type":{"value":"none"},"lon":9.183333,"surface_shortwave_radiation":{"units":"w/sqm","value":81.7},"wind_gust":{"units":"m/s","value":2.79},"precipitation":{"units":"mm/hr","value":0},"precipitation_probability":{"units":"%","value":5},"sunset":{"value":"2020-10-04T16:55:37.456Z"},"cloud_cover":{"units":"%","value":89.76},"humidity":{"units":"%","value":67.82},"wind_speed":{"units":"m/s","value":1.24},"lat":48.783333},{"temp":{"units":"C","value":11.87},"sunrise":{"value":"2020-10-04T05:27:48.253Z"},"observation_time":{"value":"2020-10-04T20:00:00.000Z"},"dewpoint":{"units":"C","value":7.96},"precipitation_type":{"value":"none"},"lon":9.183333,"surface_shortwave_radiation":{"units":"w/sqm","value":79.55},"wind_gust":{"units":"m/s","value":2.75},"precipitation":{"units":"mm/hr","value":0},"precipitation_probability":{"units":"%","value":5},"sunset":{"value":"2020-10-04T16:55:37.456Z"},"cloud_cover":{"units":"%","value":93.69},"humidity":{"units":"%","value":75.91},"wind_speed":{"units":"m/s","value":1.25},"lat":48.783333},{"temp":{"units":"C","value":11.57},"sunrise":{"value":"2020-10-04T05:27:48.253Z"},"observation_time":{"value":"2020-10-04T21:00:00.000Z"},"dewpoint":{"units":"C","value":8.4},"precipitation_type":{"value":"none"},"lon":9.183333,"surface_shortwave_radiation":{"units":"w/sqm","value":77.51},"wind_gust":{"units":"m/s","value":2.55},"precipitation":{"units":"mm/hr","value":0},"precipitation_probability":{"units":"%","value":10},"sunset":{"value":"2020-10-04T16:55:37.456Z"},"cloud_cover":{"units":"%","value":100},"humidity":{"units":"%","value":79.54},"wind_speed":{"units":"m/s","value":0.79},"lat":48.783333},{"temp":{"units":"C","value":11.09},"sunrise":{"value":"2020-10-04T05:27:48.253Z"},"observation_time":{"value":"2020-10-04T22:00:00.000Z"},"dewpoint":{"units":"C","value":8.57},"precipitation_type":{"value":"none"},"lon":9.183333,"surface_shortwave_radiation":{"units":"w/sqm","value":75.57},"wind_gust":{"units":"m/s","value":1.83},"precipitation":{"units":"mm/hr","value":0},"precipitation_probability":{"units":"%","value":10},"sunset":{"value":"2020-10-04T16:55:37.456Z"},"cloud_cover":{"units":"%","value":100},"humidity":{"units":"%","value":82.97},"wind_speed":{"units":"m/s","value":0.63},"lat":48.783333},{"temp":{"units":"C","value":10.5},"sunrise":{"value":"2020-10-04T05:27:48.253Z"},"observation_time":{"value":"2020-10-04T23:00:00.000Z"},"dewpoint":{"units":"C","value":8.66},"precipitation_type":{"value":"none"},"lon":9.183333,"surface_shortwave_radiation":{"units":"w/sqm","value":73.73},"wind_gust":{"units":"m/s","value":1.8},"precipitation":{"units":"mm/hr","value":0},"precipitation_probability":{"units":"%","value":10},"sunset":{"value":"2020-10-04T16:55:37.456Z"},"cloud_cover":{"units":"%","value":100},"humidity":{"units":"%","value":87.18},"wind_speed":{"units":"m/s","value":0.86},"lat":48.783333},{"temp":{"units":"C","value":10.86},"sunrise":{"value":"2020-10-05T05:29:16.462Z"},"observation_time":{"value":"2020-10-05T00:00:00.000Z"},"dewpoint":{"units":"C","value":7.95},"precipitation_type":{"value":"rain"},"lon":9.183333,"surface_shortwave_radiation":{"units":"w/sqm","value":71.97},"wind_gust":{"units":"m/s","value":1.5},"precipitation":{"units":"mm/hr","value":0.0781},"precipitation_probability":{"units":"%","value":20},"sunset":{"value":"2020-10-05T16:53:33.293Z"},"cloud_cover":{"units":"%","value":100},"humidity":{"units":"%","value":81.64},"wind_speed":{"units":"m/s","value":0.75},"lat":48.783333},{"temp":{"units":"C","value":10.81},"sunrise":{"value":"2020-10-05T05:29:16.462Z"},"observation_time":{"value":"2020-10-05T01:00:00.000Z"},"dewpoint":{"units":"C","value":7.62},"precipitation_type":{"value":"rain"},"lon":9.183333,"surface_shortwave_radiation":{"units":"w/sqm","value":70.3},"wind_gust":{"units":"m/s","value":2.13},"precipitation":{"units":"mm/hr","value":0.2871},"precipitation_probability":{"units":"%","value":30},"sunset":{"value":"2020-10-05T16:53:33.293Z"},"cloud_cover":{"units":"%","value":100},"humidity":{"units":"%","value":79.86},"wind_speed":{"units":"m/s","value":0.92},"lat":48.783333},{"temp":{"units":"C","value":10.36},"sunrise":{"value":"2020-10-05T05:29:16.462Z"},"observation_time":{"value":"2020-10-05T02:00:00.000Z"},"dewpoint":{"units":"C","value":8.21},"precipitation_type":{"value":"rain"},"lon":9.183333,"surface_shortwave_radiation":{"units":"w/sqm","value":68.7},"wind_gust":{"units":"m/s","value":2.2},"precipitation":{"units":"mm/hr","value":0.7539},"precipitation_probability":{"units":"%","value":35},"sunset":{"value":"2020-10-05T16:53:33.293Z"},"cloud_cover":{"units":"%","value":100},"humidity":{"units":"%","value":85.86},"wind_speed":{"units":"m/s","value":0.97},"lat":48.783333},{"temp":{"units":"C","value":10.08},"sunrise":{"value":"2020-10-05T05:29:16.462Z"},"observation_time":{"value":"2020-10-05T03:00:00.000Z"},"dewpoint":{"units":"C","value":8.61},"precipitation_type":{"value":"rain"},"lon":9.183333,"surface_shortwave_radiation":{"units":"w/sqm","value":67.17},"wind_gust":{"units":"m/s","value":2.19},"precipitation":{"units":"mm/hr","value":0.9219},"precipitation_probability":{"units":"%","value":45},"sunset":{"value":"2020-10-05T16:53:33.293Z"},"cloud_cover":{"units":"%","value":99.96},"humidity":{"units":"%","value":89.78},"wind_speed":{"units":"m/s","value":0.88},"lat":48.783333},{"temp":{"units":"C","value":9.68},"sunrise":{"value":"2020-10-05T05:29:16.462Z"},"observation_time":{"value":"2020-10-05T04:00:00.000Z"},"dewpoint":{"units":"C","value":8.61},"precipitation_type":{"value":"rain"},"lon":9.183333,"surface_shortwave_radiation":{"units":"w/sqm","value":65.71},"wind_gust":{"units":"m/s","value":1.99},"precipitation":{"units":"mm/hr","value":0.25},"precipitation_probability":{"units":"%","value":50},"sunset":{"value":"2020-10-05T16:53:33.293Z"},"cloud_cover":{"units":"%","value":99.06},"humidity":{"units":"%","value":91.97},"wind_speed":{"units":"m/s","value":0.99},"lat":48.783333},{"temp":{"units":"C","value":9.6},"sunrise":{"value":"2020-10-05T05:29:16.462Z"},"observation_time":{"value":"2020-10-05T05:00:00.000Z"},"dewpoint":{"units":"C","value":8.45},"precipitation_type":{"value":"rain"},"lon":9.183333,"surface_shortwave_radiation":{"units":"w/sqm","value":64.32},"wind_gust":{"units":"m/s","value":2.34},"precipitation":{"units":"mm/hr","value":0.2188},"precipitation_probability":{"units":"%","value":45},"sunset":{"value":"2020-10-05T16:53:33.293Z"},"cloud_cover":{"units":"%","value":100},"humidity":{"units":"%","value":91.76},"wind_speed":{"units":"m/s","value":1.02},"lat":48.783333},{"temp":{"units":"C","value":9.54},"sunrise":{"value":"2020-10-05T05:29:16.462Z"},"observation_time":{"value":"2020-10-05T06:00:00.000Z"},"dewpoint":{"units":"C","value":8.26},"precipitation_type":{"value":"rain"},"lon":9.183333,"surface_shortwave_radiation":{"units":"w/sqm","value":62.98},"wind_gust":{"units":"m/s","value":2.47},"precipitation":{"units":"mm/hr","value":0.1797},"precipitation_probability":{"units":"%","value":40},"sunset":{"value":"2020-10-05T16:53:33.293Z"},"cloud_cover":{"units":"%","value":100},"humidity":{"units":"%","value":91.16},"wind_speed":{"units":"m/s","value":1.16},"lat":48.783333},{"temp":{"units":"C","value":10.31},"sunrise":{"value":"2020-10-05T05:29:16.462Z"},"observation_time":{"value":"2020-10-05T07:00:00.000Z"},"dewpoint":{"units":"C","value":8.03},"precipitation_type":{"value":"none"},"lon":9.183333,"surface_shortwave_radiation":{"units":"w/sqm","value":61.71},"wind_gust":{"units":"m/s","value":4.26},"precipitation":{"units":"mm/hr","value":0},"precipitation_probability":{"units":"%","value":35},"sunset":{"value":"2020-10-05T16:53:33.293Z"},"cloud_cover":{"units":"%","value":100},"humidity":{"units":"%","value":84.87},"wind_speed":{"units":"m/s","value":1.87},"lat":48.783333},{"temp":{"units":"C","value":11.64},"sunrise":{"value":"2020-10-05T05:29:16.462Z"},"observation_time":{"value":"2020-10-05T08:00:00.000Z"},"dewpoint":{"units":"C","value":7.7},"precipitation_type":{"value":"none"},"lon":9.183333,"surface_shortwave_radiation":{"units":"w/sqm","value":61.63},"wind_gust":{"units":"m/s","value":8.22},"precipitation":{"units":"mm/hr","value":0},"precipitation_probability":{"units":"%","value":25},"sunset":{"value":"2020-10-05T16:53:33.293Z"},"cloud_cover":{"units":"%","value":89.11},"humidity":{"units":"%","value":75.97},"wind_speed":{"units":"m/s","value":3.65},"lat":48.783333},{"temp":{"units":"C","value":12.86},"sunrise":{"value":"2020-10-05T05:29:16.462Z"},"observation_time":{"value":"2020-10-05T09:00:00.000Z"},"dewpoint":{"units":"C","value":7.12},"precipitation_type":{"value":"none"},"lon":9.183333,"surface_shortwave_radiation":{"units":"w/sqm","value":64.02},"wind_gust":{"units":"m/s","value":9.22},"precipitation":{"units":"mm/hr","value":0},"precipitation_probability":{"units":"%","value":5},"sunset":{"value":"2020-10-05T16:53:33.293Z"},"cloud_cover":{"units":"%","value":80.7},"humidity":{"units":"%","value":68.39},"wind_speed":{"units":"m/s","value":4},"lat":48.783333},{"temp":{"units":"C","value":13.75},"sunrise":{"value":"2020-10-05T05:29:16.462Z"},"observation_time":{"value":"2020-10-05T10:00:00.000Z"},"dewpoint":{"units":"C","value":6.38},"precipitation_type":{"value":"none"},"lon":9.183333,"surface_shortwave_radiation":{"units":"w/sqm","value":67.58},"wind_gust":{"units":"m/s","value":9.89},"precipitation":{"units":"mm/hr","value":0},"precipitation_probability":{"units":"%","value":0},"sunset":{"value":"2020-10-05T16:53:33.293Z"},"cloud_cover":{"units":"%","value":95.29},"humidity":{"units":"%","value":60.34},"wind_speed":{"units":"m/s","value":4.29},"lat":48.783333},{"temp":{"units":"C","value":14.15},"sunrise":{"value":"2020-10-05T05:29:16.462Z"},"observation_time":{"value":"2020-10-05T11:00:00.000Z"},"dewpoint":{"units":"C","value":5.94},"precipitation_type":{"value":"none"},"lon":9.183333,"surface_shortwave_radiation":{"units":"w/sqm","value":67.64},"wind_gust":{"units":"m/s","value":10.77},"precipitation":{"units":"mm/hr","value":0},"precipitation_probability":{"units":"%","value":0},"sunset":{"value":"2020-10-05T16:53:33.293Z"},"cloud_cover":{"units":"%","value":100},"humidity":{"units":"%","value":56.76},"wind_speed":{"units":"m/s","value":4.74},"lat":48.783333},{"temp":{"units":"C","value":14.9},"sunrise":{"value":"2020-10-05T05:29:16.462Z"},"observation_time":{"value":"2020-10-05T12:00:00.000Z"},"dewpoint":{"units":"C","value":5.6},"precipitation_type":{"value":"none"},"lon":9.183333,"surface_shortwave_radiation":{"units":"w/sqm","value":67.03},"wind_gust":{"units":"m/s","value":10.68},"precipitation":{"units":"mm/hr","value":0},"precipitation_probability":{"units":"%","value":0},"sunset":{"value":"2020-10-05T16:53:33.293Z"},"cloud_cover":{"units":"%","value":100},"humidity":{"units":"%","value":52.74},"wind_speed":{"units":"m/s","value":4.62},"lat":48.783333},{"temp":{"units":"C","value":15.31},"sunrise":{"value":"2020-10-05T05:29:16.462Z"},"observation_time":{"value":"2020-10-05T13:00:00.000Z"},"dewpoint":{"units":"C","value":5.38},"precipitation_type":{"value":"none"},"lon":9.183333,"surface_shortwave_radiation":{"units":"w/sqm","value":69.11},"wind_gust":{"units":"m/s","value":12.29},"precipitation":{"units":"mm/hr","value":0},"precipitation_probability":{"units":"%","value":5},"sunset":{"value":"2020-10-05T16:53:33.293Z"},"cloud_cover":{"units":"%","value":90.07},"humidity":{"units":"%","value":50.76},"wind_speed":{"units":"m/s","value":5.2},"lat":48.783333},{"temp":{"units":"C","value":14.7},"sunrise":{"value":"2020-10-05T05:29:16.462Z"},"observation_time":{"value":"2020-10-05T14:00:00.000Z"},"dewpoint":{"units":"C","value":5.44},"precipitation_type":{"value":"none"},"lon":9.183333,"surface_shortwave_radiation":{"units":"w/sqm","value":69.74},"wind_gust":{"units":"m/s","value":15.55},"precipitation":{"units":"mm/hr","value":0},"precipitation_probability":{"units":"%","value":10},"sunset":{"value":"2020-10-05T16:53:33.293Z"},"cloud_cover":{"units":"%","value":99.71},"humidity":{"units":"%","value":52.94},"wind_speed":{"units":"m/s","value":5.44},"lat":48.783333},{"temp":{"units":"C","value":13.7},"sunrise":{"value":"2020-10-05T05:29:16.462Z"},"observation_time":{"value":"2020-10-05T15:00:00.000Z"},"dewpoint":{"units":"C","value":5.53},"precipitation_type":{"value":"none"},"lon":9.183333,"surface_shortwave_radiation":{"units":"w/sqm","value":68.66},"wind_gust":{"units":"m/s","value":12.36},"precipitation":{"units":"mm/hr","value":0},"precipitation_probability":{"units":"%","value":20},"sunset":{"value":"2020-10-05T16:53:33.293Z"},"cloud_cover":{"units":"%","value":100},"humidity":{"units":"%","value":56.98},"wind_speed":{"units":"m/s","value":5.48},"lat":48.783333},{"temp":{"units":"C","value":12.76},"sunrise":{"value":"2020-10-05T05:29:16.462Z"},"observation_time":{"value":"2020-10-05T16:00:00.000Z"},"dewpoint":{"units":"C","value":6.12},"precipitation_type":{"value":"rain"},"lon":9.183333,"surface_shortwave_radiation":{"units":"w/sqm","value":67.49},"wind_gust":{"units":"m/s","value":12.09},"precipitation":{"units":"mm/hr","value":0.0703},"precipitation_probability":{"units":"%","value":30},"sunset":{"value":"2020-10-05T16:53:33.293Z"},"cloud_cover":{"units":"%","value":100},"humidity":{"units":"%","value":63.32},"wind_speed":{"units":"m/s","value":5.03},"lat":48.783333},{"temp":{"units":"C","value":11.97},"sunrise":{"value":"2020-10-05T05:29:16.462Z"},"observation_time":{"value":"2020-10-05T17:00:00.000Z"},"dewpoint":{"units":"C","value":6.08},"precipitation_type":{"value":"rain"},"lon":9.183333,"surface_shortwave_radiation":{"units":"w/sqm","value":66.35},"wind_gust":{"units":"m/s","value":12.54},"precipitation":{"units":"mm/hr","value":0.0664},"precipitation_probability":{"units":"%","value":45},"sunset":{"value":"2020-10-05T16:53:33.293Z"},"cloud_cover":{"units":"%","value":99.51},"humidity":{"units":"%","value":66.53},"wind_speed":{"units":"m/s","value":5.59},"lat":48.783333},{"temp":{"units":"C","value":11.61},"sunrise":{"value":"2020-10-05T05:29:16.462Z"},"observation_time":{"value":"2020-10-05T18:00:00.000Z"},"dewpoint":{"units":"C","value":6.18},"precipitation_type":{"value":"rain"},"lon":9.183333,"surface_shortwave_radiation":{"units":"w/sqm","value":65.25},"wind_gust":{"units":"m/s","value":12.77},"precipitation":{"units":"mm/hr","value":0.0234},"precipitation_probability":{"units":"%","value":50},"sunset":{"value":"2020-10-05T16:53:33.293Z"},"cloud_cover":{"units":"%","value":92.19},"humidity":{"units":"%","value":68.53},"wind_speed":{"units":"m/s","value":5.66},"lat":48.783333},{"temp":{"units":"C","value":11.17},"sunrise":{"value":"2020-10-05T05:29:16.462Z"},"observation_time":{"value":"2020-10-05T19:00:00.000Z"},"dewpoint":{"units":"C","value":6.85},"precipitation_type":{"value":"rain"},"lon":9.183333,"surface_shortwave_radiation":{"units":"w/sqm","value":64.18},"wind_gust":{"units":"m/s","value":12.76},"precipitation":{"units":"mm/hr","value":0.1914},"precipitation_probability":{"units":"%","value":55},"sunset":{"value":"2020-10-05T16:53:33.293Z"},"cloud_cover":{"units":"%","value":100},"humidity":{"units":"%","value":74.06},"wind_speed":{"units":"m/s","value":5.53},"lat":48.783333},{"temp":{"units":"C","value":11.15},"sunrise":{"value":"2020-10-05T05:29:16.462Z"},"observation_time":{"value":"2020-10-05T20:00:00.000Z"},"dewpoint":{"units":"C","value":7.02},"precipitation_type":{"value":"rain"},"lon":9.183333,"surface_shortwave_radiation":{"units":"w/sqm","value":63.14},"wind_gust":{"units":"m/s","value":12.33},"precipitation":{"units":"mm/hr","value":0.1133},"precipitation_probability":{"units":"%","value":40},"sunset":{"value":"2020-10-05T16:53:33.293Z"},"cloud_cover":{"units":"%","value":100},"humidity":{"units":"%","value":75.18},"wind_speed":{"units":"m/s","value":5.22},"lat":48.783333},{"temp":{"units":"C","value":11.38},"sunrise":{"value":"2020-10-05T05:29:16.462Z"},"observation_time":{"value":"2020-10-05T21:00:00.000Z"},"dewpoint":{"units":"C","value":7.21},"precipitation_type":{"value":"none"},"lon":9.183333,"surface_shortwave_radiation":{"units":"w/sqm","value":62.14},"wind_gust":{"units":"m/s","value":11.5},"precipitation":{"units":"mm/hr","value":0},"precipitation_probability":{"units":"%","value":30},"sunset":{"value":"2020-10-05T16:53:33.293Z"},"cloud_cover":{"units":"%","value":100},"humidity":{"units":"%","value":74.49},"wind_speed":{"units":"m/s","value":4.93},"lat":48.783333},{"temp":{"units":"C","value":11.5},"sunrise":{"value":"2020-10-05T05:29:16.462Z"},"observation_time":{"value":"2020-10-05T22:00:00.000Z"},"dewpoint":{"units":"C","value":7.85},"precipitation_type":{"value":"none"},"lon":9.183333,"surface_shortwave_radiation":{"units":"w/sqm","value":61.17},"wind_gust":{"units":"m/s","value":11.01},"precipitation":{"units":"mm/hr","value":0},"precipitation_probability":{"units":"%","value":30},"sunset":{"value":"2020-10-05T16:53:33.293Z"},"cloud_cover":{"units":"%","value":100},"humidity":{"units":"%","value":77.07},"wind_speed":{"units":"m/s","value":4.57},"lat":48.783333},{"temp":{"units":"C","value":11.58},"sunrise":{"value":"2020-10-05T05:29:16.462Z"},"observation_time":{"value":"2020-10-05T23:00:00.000Z"},"dewpoint":{"units":"C","value":8.33},"precipitation_type":{"value":"rain"},"lon":9.183333,"surface_shortwave_radiation":{"units":"w/sqm","value":60.22},"wind_gust":{"units":"m/s","value":10.29},"precipitation":{"units":"mm/hr","value":0.0313},"precipitation_probability":{"units":"%","value":35},"sunset":{"value":"2020-10-05T16:53:33.293Z"},"cloud_cover":{"units":"%","value":100},"humidity":{"units":"%","value":79.32},"wind_speed":{"units":"m/s","value":4.62},"lat":48.783333},{"temp":{"units":"C","value":11.53},"sunrise":{"value":"2020-10-06T05:30:44.943Z"},"observation_time":{"value":"2020-10-06T00:00:00.000Z"},"dewpoint":{"units":"C","value":8.93},"precipitation_type":{"value":"rain"},"lon":9.183333,"surface_shortwave_radiation":{"units":"w/sqm","value":59.32},"wind_gust":{"units":"m/s","value":10.97},"precipitation":{"units":"mm/hr","value":0.3828},"precipitation_probability":{"units":"%","value":60},"sunset":{"value":"2020-10-06T16:51:29.626Z"},"cloud_cover":{"units":"%","value":100},"humidity":{"units":"%","value":82.95},"wind_speed":{"units":"m/s","value":4.94},"lat":48.783333},{"temp":{"units":"C","value":11.54},"sunrise":{"value":"2020-10-06T05:30:44.943Z"},"observation_time":{"value":"2020-10-06T01:00:00.000Z"},"dewpoint":{"units":"C","value":9},"precipitation_type":{"value":"rain"},"lon":9.183333,"surface_shortwave_radiation":{"units":"w/sqm","value":58.43},"wind_gust":{"units":"m/s","value":10.97},"precipitation":{"units":"mm/hr","value":0.1211},"precipitation_probability":{"units":"%","value":70},"sunset":{"value":"2020-10-06T16:51:29.626Z"},"cloud_cover":{"units":"%","value":100},"humidity":{"units":"%","value":83.22},"wind_speed":{"units":"m/s","value":4.88},"lat":48.783333},{"temp":{"units":"C","value":11.62},"sunrise":{"value":"2020-10-06T05:30:44.943Z"},"observation_time":{"value":"2020-10-06T02:00:00.000Z"},"dewpoint":{"units":"C","value":8.8},"precipitation_type":{"value":"rain"},"lon":9.183333,"surface_shortwave_radiation":{"units":"w/sqm","value":57.57},"wind_gust":{"units":"m/s","value":11.09},"precipitation":{"units":"mm/hr","value":0.1211},"precipitation_probability":{"units":"%","value":70},"sunset":{"value":"2020-10-06T16:51:29.626Z"},"cloud_cover":{"units":"%","value":100},"humidity":{"units":"%","value":81.84},"wind_speed":{"units":"m/s","value":4.94},"lat":48.783333},{"temp":{"units":"C","value":11.61},"sunrise":{"value":"2020-10-06T05:30:44.943Z"},"observation_time":{"value":"2020-10-06T03:00:00.000Z"},"dewpoint":{"units":"C","value":8.61},"precipitation_type":{"value":"rain"},"lon":9.183333,"surface_shortwave_radiation":{"units":"w/sqm","value":56.73},"wind_gust":{"units":"m/s","value":11.42},"precipitation":{"units":"mm/hr","value":0.1797},"precipitation_probability":{"units":"%","value":65},"sunset":{"value":"2020-10-06T16:51:29.626Z"},"cloud_cover":{"units":"%","value":99.51},"humidity":{"units":"%","value":81.08},"wind_speed":{"units":"m/s","value":5.18},"lat":48.783333},{"temp":{"units":"C","value":11.32},"sunrise":{"value":"2020-10-06T05:30:44.943Z"},"observation_time":{"value":"2020-10-06T04:00:00.000Z"},"dewpoint":{"units":"C","value":8.58},"precipitation_type":{"value":"rain"},"lon":9.183333,"surface_shortwave_radiation":{"units":"w/sqm","value":55.92},"wind_gust":{"units":"m/s","value":11.46},"precipitation":{"units":"mm/hr","value":0.2578},"precipitation_probability":{"units":"%","value":50},"sunset":{"value":"2020-10-06T16:51:29.626Z"},"cloud_cover":{"units":"%","value":96.36},"humidity":{"units":"%","value":82.64},"wind_speed":{"units":"m/s","value":4.93},"lat":48.783333},{"temp":{"units":"C","value":11.16},"sunrise":{"value":"2020-10-06T05:30:44.943Z"},"observation_time":{"value":"2020-10-06T05:00:00.000Z"},"dewpoint":{"units":"C","value":8.24},"precipitation_type":{"value":"rain"},"lon":9.183333,"surface_shortwave_radiation":{"units":"w/sqm","value":55.14},"wind_gust":{"units":"m/s","value":10.91},"precipitation":{"units":"mm/hr","value":0.1133},"precipitation_probability":{"units":"%","value":30},"sunset":{"value":"2020-10-06T16:51:29.626Z"},"cloud_cover":{"units":"%","value":88.77},"humidity":{"units":"%","value":81.59},"wind_speed":{"units":"m/s","value":4.4},"lat":48.783333},{"temp":{"units":"C","value":11.16},"sunrise":{"value":"2020-10-06T05:30:44.943Z"},"observation_time":{"value":"2020-10-06T06:00:00.000Z"},"dewpoint":{"units":"C","value":7.97},"precipitation_type":{"value":"none"},"lon":9.183333,"surface_shortwave_radiation":{"units":"w/sqm","value":54.37},"wind_gust":{"units":"m/s","value":9.81},"precipitation":{"units":"mm/hr","value":0},"precipitation_probability":{"units":"%","value":15},"sunset":{"value":"2020-10-06T16:51:29.626Z"},"cloud_cover":{"units":"%","value":92.55},"humidity":{"units":"%","value":80.11},"wind_speed":{"units":"m/s","value":4.3},"lat":48.783333},{"temp":{"units":"C","value":11.41},"sunrise":{"value":"2020-10-06T05:30:44.943Z"},"observation_time":{"value":"2020-10-06T07:00:00.000Z"},"dewpoint":{"units":"C","value":7.59},"precipitation_type":{"value":"none"},"lon":9.183333,"surface_shortwave_radiation":{"units":"w/sqm","value":53.89},"wind_gust":{"units":"m/s","value":9.48},"precipitation":{"units":"mm/hr","value":0},"precipitation_probability":{"units":"%","value":5},"sunset":{"value":"2020-10-06T16:51:29.626Z"},"cloud_cover":{"units":"%","value":95.86},"humidity":{"units":"%","value":76.56},"wind_speed":{"units":"m/s","value":4.2},"lat":48.783333},{"temp":{"units":"C","value":12.22},"sunrise":{"value":"2020-10-06T05:30:44.943Z"},"observation_time":{"value":"2020-10-06T08:00:00.000Z"},"dewpoint":{"units":"C","value":7.08},"precipitation_type":{"value":"none"},"lon":9.183333,"surface_shortwave_radiation":{"units":"w/sqm","value":54.76},"wind_gust":{"units":"m/s","value":9.56},"precipitation":{"units":"mm/hr","value":0},"precipitation_probability":{"units":"%","value":0},"sunset":{"value":"2020-10-06T16:51:29.626Z"},"cloud_cover":{"units":"%","value":86.9},"humidity":{"units":"%","value":70.03},"wind_speed":{"units":"m/s","value":4.21},"lat":48.783333},{"temp":{"units":"C","value":13.17},"sunrise":{"value":"2020-10-06T05:30:44.943Z"},"observation_time":{"value":"2020-10-06T09:00:00.000Z"},"dewpoint":{"units":"C","value":6.95},"precipitation_type":{"value":"none"},"lon":9.183333,"surface_shortwave_radiation":{"units":"w/sqm","value":55.86},"wind_gust":{"units":"m/s","value":11.31},"precipitation":{"units":"mm/hr","value":0},"precipitation_probability":{"units":"%","value":0},"sunset":{"value":"2020-10-06T16:51:29.626Z"},"cloud_cover":{"units":"%","value":91.53},"humidity":{"units":"%","value":65.32},"wind_speed":{"units":"m/s","value":4.73},"lat":48.783333},{"temp":{"units":"C","value":14.12},"sunrise":{"value":"2020-10-06T05:30:44.943Z"},"observation_time":{"value":"2020-10-06T10:00:00.000Z"},"dewpoint":{"units":"C","value":7.16},"precipitation_type":{"value":"none"},"lon":9.183333,"surface_shortwave_radiation":{"units":"w/sqm","value":56.23},"wind_gust":{"units":"m/s","value":11.02},"precipitation":{"units":"mm/hr","value":0},"precipitation_probability":{"units":"%","value":0},"sunset":{"value":"2020-10-06T16:51:29.626Z"},"cloud_cover":{"units":"%","value":100},"humidity":{"units":"%","value":62.07},"wind_speed":{"units":"m/s","value":4.1},"lat":48.783333},{"temp":{"units":"C","value":14.67},"sunrise":{"value":"2020-10-06T05:30:44.943Z"},"observation_time":{"value":"2020-10-06T11:00:00.000Z"},"dewpoint":{"units":"C","value":6.93},"precipitation_type":{"value":"none"},"lon":9.183333,"surface_shortwave_radiation":{"units":"w/sqm","value":55.94},"wind_gust":{"units":"m/s","value":10.44},"precipitation":{"units":"mm/hr","value":0},"precipitation_probability":{"units":"%","value":10},"sunset":{"value":"2020-10-06T16:51:29.626Z"},"cloud_cover":{"units":"%","value":99.29},"humidity":{"units":"%","value":59.24},"wind_speed":{"units":"m/s","value":4.61},"lat":48.783333},{"temp":{"units":"C","value":14.88},"sunrise":{"value":"2020-10-06T05:30:44.943Z"},"observation_time":{"value":"2020-10-06T12:00:00.000Z"},"dewpoint":{"units":"C","value":6.96},"precipitation_type":{"value":"rain"},"lon":9.183333,"surface_shortwave_radiation":{"units":"w/sqm","value":55.94},"wind_gust":{"units":"m/s","value":11.18},"precipitation":{"units":"mm/hr","value":0.043},"precipitation_probability":{"units":"%","value":30},"sunset":{"value":"2020-10-06T16:51:29.626Z"},"cloud_cover":{"units":"%","value":100},"humidity":{"units":"%","value":58.24},"wind_speed":{"units":"m/s","value":4.64},"lat":48.783333},{"temp":{"units":"C","value":14.88},"sunrise":{"value":"2020-10-06T05:30:44.943Z"},"observation_time":{"value":"2020-10-06T13:00:00.000Z"},"dewpoint":{"units":"C","value":6.96},"precipitation_type":{"value":"rain"},"lon":9.183333,"surface_shortwave_radiation":{"units":"w/sqm","value":55.94},"wind_gust":{"units":"m/s","value":11.18},"precipitation":{"units":"mm/hr","value":0.043},"precipitation_probability":{"units":"%","value":30},"sunset":{"value":"2020-10-06T16:51:29.626Z"},"cloud_cover":{"units":"%","value":100},"humidity":{"units":"%","value":58.24},"wind_speed":{"units":"m/s","value":4.64},"lat":48.783333},{"temp":{"units":"C","value":14.88},"sunrise":{"value":"2020-10-06T05:30:44.943Z"},"observation_time":{"value":"2020-10-06T14:00:00.000Z"},"dewpoint":{"units":"C","value":6.96},"precipitation_type":{"value":"rain"},"lon":9.183333,"surface_shortwave_radiation":{"units":"w/sqm","value":55.94},"wind_gust":{"units":"m/s","value":11.18},"precipitation":{"units":"mm/hr","value":0.043},"precipitation_probability":{"units":"%","value":30},"sunset":{"value":"2020-10-06T16:51:29.626Z"},"cloud_cover":{"units":"%","value":100},"humidity":{"units":"%","value":58.24},"wind_speed":{"units":"m/s","value":4.64},"lat":48.783333},{"temp":{"units":"C","value":12.09},"sunrise":{"value":"2020-10-06T05:30:44.943Z"},"observation_time":{"value":"2020-10-06T15:00:00.000Z"},"dewpoint":{"units":"C","value":9.17},"precipitation_type":{"value":"rain"},"lon":9.183333,"surface_shortwave_radiation":{"units":"w/sqm","value":53.93},"wind_gust":{"units":"m/s","value":10.68},"precipitation":{"units":"mm/hr","value":5.4414},"precipitation_probability":{"units":"%","value":95},"sunset":{"value":"2020-10-06T16:51:29.626Z"},"cloud_cover":{"units":"%","value":100},"humidity":{"units":"%","value":81.82},"wind_speed":{"units":"m/s","value":4.67},"lat":48.783333},{"temp":{"units":"C","value":12.09},"sunrise":{"value":"2020-10-06T05:30:44.943Z"},"observation_time":{"value":"2020-10-06T16:00:00.000Z"},"dewpoint":{"units":"C","value":9.17},"precipitation_type":{"value":"rain"},"lon":9.183333,"surface_shortwave_radiation":{"units":"w/sqm","value":53.93},"wind_gust":{"units":"m/s","value":10.68},"precipitation":{"units":"mm/hr","value":5.4414},"precipitation_probability":{"units":"%","value":95},"sunset":{"value":"2020-10-06T16:51:29.626Z"},"cloud_cover":{"units":"%","value":100},"humidity":{"units":"%","value":81.82},"wind_speed":{"units":"m/s","value":4.67},"lat":48.783333},{"temp":{"units":"C","value":12.09},"sunrise":{"value":"2020-10-06T05:30:44.943Z"},"observation_time":{"value":"2020-10-06T17:00:00.000Z"},"dewpoint":{"units":"C","value":9.17},"precipitation_type":{"value":"rain"},"lon":9.183333,"surface_shortwave_radiation":{"units":"w/sqm","value":53.93},"wind_gust":{"units":"m/s","value":10.68},"precipitation":{"units":"mm/hr","value":5.4414},"precipitation_probability":{"units":"%","value":95},"sunset":{"value":"2020-10-06T16:51:29.626Z"},"cloud_cover":{"units":"%","value":100},"humidity":{"units":"%","value":81.82},"wind_speed":{"units":"m/s","value":4.67},"lat":48.783333},{"temp":{"units":"C","value":11.99},"sunrise":{"value":"2020-10-06T05:30:44.943Z"},"observation_time":{"value":"2020-10-06T18:00:00.000Z"},"dewpoint":{"units":"C","value":9.36},"precipitation_type":{"value":"rain"},"lon":9.183333,"surface_shortwave_radiation":{"units":"w/sqm","value":52.03},"wind_gust":{"units":"m/s","value":10.26},"precipitation":{"units":"mm/hr","value":0.1133},"precipitation_probability":{"units":"%","value":85},"sunset":{"value":"2020-10-06T16:51:29.626Z"},"cloud_cover":{"units":"%","value":100},"humidity":{"units":"%","value":83.69},"wind_speed":{"units":"m/s","value":4.59},"lat":48.783333},{"temp":{"units":"C","value":11.99},"sunrise":{"value":"2020-10-06T05:30:44.943Z"},"observation_time":{"value":"2020-10-06T19:00:00.000Z"},"dewpoint":{"units":"C","value":9.36},"precipitation_type":{"value":"rain"},"lon":9.183333,"surface_shortwave_radiation":{"units":"w/sqm","value":52.03},"wind_gust":{"units":"m/s","value":10.26},"precipitation":{"units":"mm/hr","value":0.1133},"precipitation_probability":{"units":"%","value":85},"sunset":{"value":"2020-10-06T16:51:29.626Z"},"cloud_cover":{"units":"%","value":100},"humidity":{"units":"%","value":83.69},"wind_speed":{"units":"m/s","value":4.59},"lat":48.783333},{"temp":{"units":"C","value":11.99},"sunrise":{"value":"2020-10-06T05:30:44.943Z"},"observation_time":{"value":"2020-10-06T20:00:00.000Z"},"dewpoint":{"units":"C","value":9.36},"precipitation_type":{"value":"rain"},"lon":9.183333,"surface_shortwave_radiation":{"units":"w/sqm","value":52.03},"wind_gust":{"units":"m/s","value":10.26},"precipitation":{"units":"mm/hr","value":0.1133},"precipitation_probability":{"units":"%","value":85},"sunset":{"value":"2020-10-06T16:51:29.626Z"},"cloud_cover":{"units":"%","value":100},"humidity":{"units":"%","value":83.69},"wind_speed":{"units":"m/s","value":4.59},"lat":48.783333},{"temp":{"units":"C","value":12.4},"sunrise":{"value":"2020-10-06T05:30:44.943Z"},"observation_time":{"value":"2020-10-06T21:00:00.000Z"},"dewpoint":{"units":"C","value":9.88},"precipitation_type":{"value":"rain"},"lon":9.183333,"surface_shortwave_radiation":{"units":"w/sqm","value":50.23},"wind_gust":{"units":"m/s","value":9.43},"precipitation":{"units":"mm/hr","value":0.1641},"precipitation_probability":{"units":"%","value":50},"sunset":{"value":"2020-10-06T16:51:29.626Z"},"cloud_cover":{"units":"%","value":70.47},"humidity":{"units":"%","value":83.25},"wind_speed":{"units":"m/s","value":2.84},"lat":48.783333},{"temp":{"units":"C","value":12.4},"sunrise":{"value":"2020-10-06T05:30:44.943Z"},"observation_time":{"value":"2020-10-06T22:00:00.000Z"},"dewpoint":{"units":"C","value":9.88},"precipitation_type":{"value":"rain"},"lon":9.183333,"surface_shortwave_radiation":{"units":"w/sqm","value":50.23},"wind_gust":{"units":"m/s","value":9.43},"precipitation":{"units":"mm/hr","value":0.1641},"precipitation_probability":{"units":"%","value":50},"sunset":{"value":"2020-10-06T16:51:29.626Z"},"cloud_cover":{"units":"%","value":70.47},"humidity":{"units":"%","value":83.25},"wind_speed":{"units":"m/s","value":2.84},"lat":48.783333},{"temp":{"units":"C","value":12.4},"sunrise":{"value":"2020-10-06T05:30:44.943Z"},"observation_time":{"value":"2020-10-06T23:00:00.000Z"},"dewpoint":{"units":"C","value":9.88},"precipitation_type":{"value":"rain"},"lon":9.183333,"surface_shortwave_radiation":{"units":"w/sqm","value":50.23},"wind_gust":{"units":"m/s","value":9.43},"precipitation":{"units":"mm/hr","value":0.1641},"precipitation_probability":{"units":"%","value":50},"sunset":{"value":"2020-10-06T16:51:29.626Z"},"cloud_cover":{"units":"%","value":70.47},"humidity":{"units":"%","value":83.25},"wind_speed":{"units":"m/s","value":2.84},"lat":48.783333},{"temp":{"units":"C","value":11.59},"sunrise":{"value":"2020-10-07T05:32:13.705Z"},"observation_time":{"value":"2020-10-07T00:00:00.000Z"},"dewpoint":{"units":"C","value":8.6},"precipitation_type":{"value":"none"},"lon":9.183333,"surface_shortwave_radiation":{"units":"w/sqm","value":48.56},"wind_gust":{"units":"m/s","value":5.77},"precipitation":{"units":"mm/hr","value":0},"precipitation_probability":{"units":"%","value":30},"sunset":{"value":"2020-10-07T16:49:26.492Z"},"cloud_cover":{"units":"%","value":100},"humidity":{"units":"%","value":81.94},"wind_speed":{"units":"m/s","value":2.37},"lat":48.783333},{"temp":{"units":"C","value":11.59},"sunrise":{"value":"2020-10-07T05:32:13.705Z"},"observation_time":{"value":"2020-10-07T01:00:00.000Z"},"dewpoint":{"units":"C","value":8.6},"precipitation_type":{"value":"none"},"lon":9.183333,"surface_shortwave_radiation":{"units":"w/sqm","value":48.56},"wind_gust":{"units":"m/s","value":5.77},"precipitation":{"units":"mm/hr","value":0},"precipitation_probability":{"units":"%","value":30},"sunset":{"value":"2020-10-07T16:49:26.492Z"},"cloud_cover":{"units":"%","value":100},"humidity":{"units":"%","value":81.94},"wind_speed":{"units":"m/s","value":2.37},"lat":48.783333},{"temp":{"units":"C","value":11.59},"sunrise":{"value":"2020-10-07T05:32:13.705Z"},"observation_time":{"value":"2020-10-07T02:00:00.000Z"},"dewpoint":{"units":"C","value":8.6},"precipitation_type":{"value":"none"},"lon":9.183333,"surface_shortwave_radiation":{"units":"w/sqm","value":48.56},"wind_gust":{"units":"m/s","value":5.77},"precipitation":{"units":"mm/hr","value":0},"precipitation_probability":{"units":"%","value":30},"sunset":{"value":"2020-10-07T16:49:26.492Z"},"cloud_cover":{"units":"%","value":100},"humidity":{"units":"%","value":81.94},"wind_speed":{"units":"m/s","value":2.37},"lat":48.783333},{"temp":{"units":"C","value":11.43},"sunrise":{"value":"2020-10-07T05:32:13.705Z"},"observation_time":{"value":"2020-10-07T03:00:00.000Z"},"dewpoint":{"units":"C","value":8.55},"precipitation_type":{"value":"rain"},"lon":9.183333,"surface_shortwave_radiation":{"units":"w/sqm","value":46.99},"wind_gust":{"units":"m/s","value":6.7},"precipitation":{"units":"mm/hr","value":0.1055},"precipitation_probability":{"units":"%","value":60},"sunset":{"value":"2020-10-07T16:49:26.492Z"},"cloud_cover":{"units":"%","value":100},"humidity":{"units":"%","value":82.12},"wind_speed":{"units":"m/s","value":2.94},"lat":48.783333},{"temp":{"units":"C","value":11.43},"sunrise":{"value":"2020-10-07T05:32:13.705Z"},"observation_time":{"value":"2020-10-07T04:00:00.000Z"},"dewpoint":{"units":"C","value":8.55},"precipitation_type":{"value":"rain"},"lon":9.183333,"surface_shortwave_radiation":{"units":"w/sqm","value":46.99},"wind_gust":{"units":"m/s","value":6.7},"precipitation":{"units":"mm/hr","value":0.1055},"precipitation_probability":{"units":"%","value":60},"sunset":{"value":"2020-10-07T16:49:26.492Z"},"cloud_cover":{"units":"%","value":100},"humidity":{"units":"%","value":82.12},"wind_speed":{"units":"m/s","value":2.94},"lat":48.783333},{"temp":{"units":"C","value":11.43},"sunrise":{"value":"2020-10-07T05:32:13.705Z"},"observation_time":{"value":"2020-10-07T05:00:00.000Z"},"dewpoint":{"units":"C","value":8.55},"precipitation_type":{"value":"rain"},"lon":9.183333,"surface_shortwave_radiation":{"units":"w/sqm","value":46.99},"wind_gust":{"units":"m/s","value":6.7},"precipitation":{"units":"mm/hr","value":0.1055},"precipitation_probability":{"units":"%","value":60},"sunset":{"value":"2020-10-07T16:49:26.492Z"},"cloud_cover":{"units":"%","value":100},"humidity":{"units":"%","value":82.12},"wind_speed":{"units":"m/s","value":2.94},"lat":48.783333},{"temp":{"units":"C","value":11.2},"sunrise":{"value":"2020-10-07T05:32:13.705Z"},"observation_time":{"value":"2020-10-07T06:00:00.000Z"},"dewpoint":{"units":"C","value":8.35},"precipitation_type":{"value":"rain"},"lon":9.183333,"surface_shortwave_radiation":{"units":"w/sqm","value":45.53},"wind_gust":{"units":"m/s","value":7.96},"precipitation":{"units":"mm/hr","value":0.457},"precipitation_probability":{"units":"%","value":80},"sunset":{"value":"2020-10-07T16:49:26.492Z"},"cloud_cover":{"units":"%","value":100},"humidity":{"units":"%","value":82.23},"wind_speed":{"units":"m/s","value":3.45},"lat":48.783333},{"temp":{"units":"C","value":11.2},"sunrise":{"value":"2020-10-07T05:32:13.705Z"},"observation_time":{"value":"2020-10-07T07:00:00.000Z"},"dewpoint":{"units":"C","value":8.35},"precipitation_type":{"value":"rain"},"lon":9.183333,"surface_shortwave_radiation":{"units":"w/sqm","value":45.53},"wind_gust":{"units":"m/s","value":7.96},"precipitation":{"units":"mm/hr","value":0.457},"precipitation_probability":{"units":"%","value":80},"sunset":{"value":"2020-10-07T16:49:26.492Z"},"cloud_cover":{"units":"%","value":100},"humidity":{"units":"%","value":82.23},"wind_speed":{"units":"m/s","value":3.45},"lat":48.783333},{"temp":{"units":"C","value":11.2},"sunrise":{"value":"2020-10-07T05:32:13.705Z"},"observation_time":{"value":"2020-10-07T08:00:00.000Z"},"dewpoint":{"units":"C","value":8.35},"precipitation_type":{"value":"rain"},"lon":9.183333,"surface_shortwave_radiation":{"units":"w/sqm","value":45.53},"wind_gust":{"units":"m/s","value":7.96},"precipitation":{"units":"mm/hr","value":0.457},"precipitation_probability":{"units":"%","value":80},"sunset":{"value":"2020-10-07T16:49:26.492Z"},"cloud_cover":{"units":"%","value":100},"humidity":{"units":"%","value":82.23},"wind_speed":{"units":"m/s","value":3.45},"lat":48.783333},{"temp":{"units":"C","value":12.33},"sunrise":{"value":"2020-10-07T05:32:13.705Z"},"observation_time":{"value":"2020-10-07T09:00:00.000Z"},"dewpoint":{"units":"C","value":8.44},"precipitation_type":{"value":"rain"},"lon":9.183333,"surface_shortwave_radiation":{"units":"w/sqm","value":44.34},"wind_gust":{"units":"m/s","value":11.82},"precipitation":{"units":"mm/hr","value":0.875},"precipitation_probability":{"units":"%","value":75},"sunset":{"value":"2020-10-07T16:49:26.492Z"},"cloud_cover":{"units":"%","value":98.31},"humidity":{"units":"%","value":76.35},"wind_speed":{"units":"m/s","value":4.46},"lat":48.783333},{"temp":{"units":"C","value":12.33},"sunrise":{"value":"2020-10-07T05:32:13.705Z"},"observation_time":{"value":"2020-10-07T10:00:00.000Z"},"dewpoint":{"units":"C","value":8.44},"precipitation_type":{"value":"rain"},"lon":9.183333,"surface_shortwave_radiation":{"units":"w/sqm","value":44.34},"wind_gust":{"units":"m/s","value":11.82},"precipitation":{"units":"mm/hr","value":0.875},"precipitation_probability":{"units":"%","value":75},"sunset":{"value":"2020-10-07T16:49:26.492Z"},"cloud_cover":{"units":"%","value":98.31},"humidity":{"units":"%","value":76.35},"wind_speed":{"units":"m/s","value":4.46},"lat":48.783333},{"temp":{"units":"C","value":12.33},"sunrise":{"value":"2020-10-07T05:32:13.705Z"},"observation_time":{"value":"2020-10-07T11:00:00.000Z"},"dewpoint":{"units":"C","value":8.44},"precipitation_type":{"value":"rain"},"lon":9.183333,"surface_shortwave_radiation":{"units":"w/sqm","value":44.34},"wind_gust":{"units":"m/s","value":11.82},"precipitation":{"units":"mm/hr","value":0.875},"precipitation_probability":{"units":"%","value":75},"sunset":{"value":"2020-10-07T16:49:26.492Z"},"cloud_cover":{"units":"%","value":98.31},"humidity":{"units":"%","value":76.35},"wind_speed":{"units":"m/s","value":4.46},"lat":48.783333},{"temp":{"units":"C","value":14.29},"sunrise":{"value":"2020-10-07T05:32:13.705Z"},"observation_time":{"value":"2020-10-07T12:00:00.000Z"},"dewpoint":{"units":"C","value":8.04},"precipitation_type":{"value":"rain"},"lon":9.183333,"surface_shortwave_radiation":{"units":"w/sqm","value":44.23},"wind_gust":{"units":"m/s","value":14.24},"precipitation":{"units":"mm/hr","value":0.3906},"precipitation_probability":{"units":"%","value":85},"sunset":{"value":"2020-10-07T16:49:26.492Z"},"cloud_cover":{"units":"%","value":94.23},"humidity":{"units":"%","value":65.45},"wind_speed":{"units":"m/s","value":5.04},"lat":48.783333},{"temp":{"units":"C","value":14.29},"sunrise":{"value":"2020-10-07T05:32:13.705Z"},"observation_time":{"value":"2020-10-07T13:00:00.000Z"},"dewpoint":{"units":"C","value":8.04},"precipitation_type":{"value":"rain"},"lon":9.183333,"surface_shortwave_radiation":{"units":"w/sqm","value":44.23},"wind_gust":{"units":"m/s","value":14.24},"precipitation":{"units":"mm/hr","value":0.3906},"precipitation_probability":{"units":"%","value":85},"sunset":{"value":"2020-10-07T16:49:26.492Z"},"cloud_cover":{"units":"%","value":94.23},"humidity":{"units":"%","value":65.45},"wind_speed":{"units":"m/s","value":5.04},"lat":48.783333},{"temp":{"units":"C","value":14.29},"sunrise":{"value":"2020-10-07T05:32:13.705Z"},"observation_time":{"value":"2020-10-07T14:00:00.000Z"},"dewpoint":{"units":"C","value":8.04},"precipitation_type":{"value":"rain"},"lon":9.183333,"surface_shortwave_radiation":{"units":"w/sqm","value":44.23},"wind_gust":{"units":"m/s","value":14.24},"precipitation":{"units":"mm/hr","value":0.3906},"precipitation_probability":{"units":"%","value":85},"sunset":{"value":"2020-10-07T16:49:26.492Z"},"cloud_cover":{"units":"%","value":94.23},"humidity":{"units":"%","value":65.45},"wind_speed":{"units":"m/s","value":5.04},"lat":48.783333},{"temp":{"units":"C","value":13.85},"sunrise":{"value":"2020-10-07T05:32:13.705Z"},"observation_time":{"value":"2020-10-07T15:00:00.000Z"},"dewpoint":{"units":"C","value":7.71},"precipitation_type":{"value":"rain"},"lon":9.183333,"surface_shortwave_radiation":{"units":"w/sqm","value":43.96},"wind_gust":{"units":"m/s","value":12.31},"precipitation":{"units":"mm/hr","value":0.4922},"precipitation_probability":{"units":"%","value":75},"sunset":{"value":"2020-10-07T16:49:26.492Z"},"cloud_cover":{"units":"%","value":88.48},"humidity":{"units":"%","value":65.78},"wind_speed":{"units":"m/s","value":3.9},"lat":48.783333},{"temp":{"units":"C","value":13.85},"sunrise":{"value":"2020-10-07T05:32:13.705Z"},"observation_time":{"value":"2020-10-07T16:00:00.000Z"},"dewpoint":{"units":"C","value":7.71},"precipitation_type":{"value":"rain"},"lon":9.183333,"surface_shortwave_radiation":{"units":"w/sqm","value":43.96},"wind_gust":{"units":"m/s","value":12.31},"precipitation":{"units":"mm/hr","value":0.4922},"precipitation_probability":{"units":"%","value":75},"sunset":{"value":"2020-10-07T16:49:26.492Z"},"cloud_cover":{"units":"%","value":88.48},"humidity":{"units":"%","value":65.78},"wind_speed":{"units":"m/s","value":3.9},"lat":48.783333},{"temp":{"units":"C","value":13.85},"sunrise":{"value":"2020-10-07T05:32:13.705Z"},"observation_time":{"value":"2020-10-07T17:00:00.000Z"},"dewpoint":{"units":"C","value":7.71},"precipitation_type":{"value":"rain"},"lon":9.183333,"surface_shortwave_radiation":{"units":"w/sqm","value":43.96},"wind_gust":{"units":"m/s","value":12.31},"precipitation":{"units":"mm/hr","value":0.4922},"precipitation_probability":{"units":"%","value":75},"sunset":{"value":"2020-10-07T16:49:26.492Z"},"cloud_cover":{"units":"%","value":88.48},"humidity":{"units":"%","value":65.78},"wind_speed":{"units":"m/s","value":3.9},"lat":48.783333},{"temp":{"units":"C","value":11.98},"sunrise":{"value":"2020-10-07T05:32:13.705Z"},"observation_time":{"value":"2020-10-07T18:00:00.000Z"},"dewpoint":{"units":"C","value":7.86},"precipitation_type":{"value":"rain"},"lon":9.183333,"surface_shortwave_radiation":{"units":"w/sqm","value":42.87},"wind_gust":{"units":"m/s","value":6.82},"precipitation":{"units":"mm/hr","value":0.9961},"precipitation_probability":{"units":"%","value":50},"sunset":{"value":"2020-10-07T16:49:26.492Z"},"cloud_cover":{"units":"%","value":100},"humidity":{"units":"%","value":75.64},"wind_speed":{"units":"m/s","value":2.74},"lat":48.783333},{"temp":{"units":"C","value":11.98},"sunrise":{"value":"2020-10-07T05:32:13.705Z"},"observation_time":{"value":"2020-10-07T19:00:00.000Z"},"dewpoint":{"units":"C","value":7.86},"precipitation_type":{"value":"rain"},"lon":9.183333,"surface_shortwave_radiation":{"units":"w/sqm","value":42.87},"wind_gust":{"units":"m/s","value":6.82},"precipitation":{"units":"mm/hr","value":0.9961},"precipitation_probability":{"units":"%","value":50},"sunset":{"value":"2020-10-07T16:49:26.492Z"},"cloud_cover":{"units":"%","value":100},"humidity":{"units":"%","value":75.64},"wind_speed":{"units":"m/s","value":2.74},"lat":48.783333},{"temp":{"units":"C","value":11.98},"sunrise":{"value":"2020-10-07T05:32:13.705Z"},"observation_time":{"value":"2020-10-07T20:00:00.000Z"},"dewpoint":{"units":"C","value":7.86},"precipitation_type":{"value":"rain"},"lon":9.183333,"surface_shortwave_radiation":{"units":"w/sqm","value":42.87},"wind_gust":{"units":"m/s","value":6.82},"precipitation":{"units":"mm/hr","value":0.9961},"precipitation_probability":{"units":"%","value":50},"sunset":{"value":"2020-10-07T16:49:26.492Z"},"cloud_cover":{"units":"%","value":100},"humidity":{"units":"%","value":75.64},"wind_speed":{"units":"m/s","value":2.74},"lat":48.783333},{"temp":{"units":"C","value":11.11},"sunrise":{"value":"2020-10-07T05:32:13.705Z"},"observation_time":{"value":"2020-10-07T21:00:00.000Z"},"dewpoint":{"units":"C","value":8.42},"precipitation_type":{"value":"rain"},"lon":9.183333,"surface_shortwave_radiation":{"units":"w/sqm","value":41.71},"wind_gust":{"units":"m/s","value":5.39},"precipitation":{"units":"mm/hr","value":0.0313},"precipitation_probability":{"units":"%","value":30},"sunset":{"value":"2020-10-07T16:49:26.492Z"},"cloud_cover":{"units":"%","value":83.29},"humidity":{"units":"%","value":83.41},"wind_speed":{"units":"m/s","value":2.41},"lat":48.783333},{"temp":{"units":"C","value":11.11},"sunrise":{"value":"2020-10-07T05:32:13.705Z"},"observation_time":{"value":"2020-10-07T22:00:00.000Z"},"dewpoint":{"units":"C","value":8.42},"precipitation_type":{"value":"rain"},"lon":9.183333,"surface_shortwave_radiation":{"units":"w/sqm","value":41.71},"wind_gust":{"units":"m/s","value":5.39},"precipitation":{"units":"mm/hr","value":0.0313},"precipitation_probability":{"units":"%","value":30},"sunset":{"value":"2020-10-07T16:49:26.492Z"},"cloud_cover":{"units":"%","value":83.29},"humidity":{"units":"%","value":83.41},"wind_speed":{"units":"m/s","value":2.41},"lat":48.783333},{"temp":{"units":"C","value":11.11},"sunrise":{"value":"2020-10-07T05:32:13.705Z"},"observation_time":{"value":"2020-10-07T23:00:00.000Z"},"dewpoint":{"units":"C","value":8.42},"precipitation_type":{"value":"rain"},"lon":9.183333,"surface_shortwave_radiation":{"units":"w/sqm","value":41.71},"wind_gust":{"units":"m/s","value":5.39},"precipitation":{"units":"mm/hr","value":0.0313},"precipitation_probability":{"units":"%","value":30},"sunset":{"value":"2020-10-07T16:49:26.492Z"},"cloud_cover":{"units":"%","value":83.29},"humidity":{"units":"%","value":83.41},"wind_speed":{"units":"m/s","value":2.41},"lat":48.783333},{"temp":{"units":"C","value":11.11},"sunrise":{"value":"2020-10-08T05:33:42.754Z"},"observation_time":{"value":"2020-10-08T00:00:00.000Z"},"dewpoint":{"units":"C","value":8.42},"precipitation_type":{"value":"rain"},"lon":9.183333,"surface_shortwave_radiation":{"units":"w/sqm","value":41.71},"wind_gust":{"units":"m/s","value":5.39},"precipitation":{"units":"mm/hr","value":0.0313},"precipitation_probability":{"units":"%","value":30},"sunset":{"value":"2020-10-08T16:47:23.921Z"},"cloud_cover":{"units":"%","value":83.29},"humidity":{"units":"%","value":83.41},"wind_speed":{"units":"m/s","value":2.41},"lat":48.783333}]