[{"temp":{"units":"C","value":2.12},"sunrise":{"value":"2020-11-28T06:51:56.610Z"},"observation_time":{"value":"2020-11-28T19:00:00.000Z"},"dewpoint":{"units":"C","value":1.09},"precipitation_type":{"value":"none"},"lon":9.183333,"surface_shortwave_radiation":{"units":"w/sqm","value":0},"wind_gust":{"units":"m/s","value":6.2},"precipitation":{"units":"mm/hr","value":0},"precipitation_probability":{"units":"%","value":0},"sunset":{"value":"2020-11-28T15:31:07.733Z"},"cloud_cover":{"units":"%","value":100},"humidity":{"units":"%","value":92.41},"wind_speed":{"units":"m/s","value":2.68},"lat":48.783333},{"temp":{"units":"C","value":2.09},"sunrise":{"value":"2020-11-28T06:51:56.610Z"},"observation_time":{"value":"2020-11-28T20:00:00.000Z"},"dewpoint":{"units":"C","value":1.18},"precipitation_type":{"value":"none"},"lon":9.183333,"surface_shortwave_radiation":{"units":"w/sqm","value":0},"wind_gust":{"units":"m/s","value":6.07},"precipitation":{"units":"mm/hr","value":0},"precipitation_probability":{"units":"%","value":0},"sunset":{"value":"2020-11-28T15:31:07.733Z"},"cloud_cover":{"units":"%","value":100},"humidity":{"units":"%","value":93.47},"wind_speed":{"units":"m/s","value":2.45},"lat":48.783333},{"temp":{"units":"C","value":2.2},"sunrise":{"value":"2020-11-28T06:51:56.610Z"},"observation_time":{"value":"2020-11-28T21:00:00.000Z"},"dewpoint":{"units":"C","value":1.27},"precipitation_type":{"value":"none"},"lon":9.183333,"surface_shortwave_radiation":{"units":"w/sqm","value":0},"wind_gust":{"units":"m/s","value":5.37},"precipitation":{"units":"mm/hr","value":0},"precipitation_probability":{"units":"%","value":0},"sunset":{"value":"2020-11-28T15:31:07.733Z"},"cloud_cover":{"units":"%","value":100},"humidity":{"units":"%","value":93.02},"wind_speed":{"units":"m/s","value":2.24},"lat":48.783333},{"temp":{"units":"C","value":2.29},"sunrise":{"value":"2020-11-28T06:51:56.610Z"},"observation_time":{"value":"2020-11-28T22:00:00.000Z"},"dewpoint":{"units":"C","value":1.25},"precipitation_type":{"value":"none"},"lon":9.183333,"surface_shortwave_radiation":{"units":"w/sqm","value":0},"wind_gust":{"units":"m/s","value":5.41},"precipitation":{"units":"mm/hr","value":0},"precipitation_probability":{"units":"%","value":0},"sunset":{"value":"2020-11-28T15:31:07.733Z"},"cloud_cover":{"units":"%","value":100},"humidity":{"units":"%","value":92.28},"wind_speed":{"units":"m/s","value":2.3},"lat":48.783333},{"temp":{"units":"C","value":2.41},"sunrise":{"value":"2020-11-28T06:51:56.610Z"},"observation_time":{"value":"2020-11-28T23:00:00.000Z"},"dewpoint":{"units":"C","value":1.36},"precipitation_type":{"value":"none"},"lon":9.183333,"surface_shortwave_radiation":{"units":"w/sqm","value":0},"wind_gust":{"units":"m/s","value":5.35},"precipitation":{"units":"mm/hr","value":0},"precipitation_probability":{"units":"%","value":0},"sunset":{"value":"2020-11-28T15:31:07.733Z"},"cloud_cover":{"units":"%","value":100},"humidity":{"units":"%","value":92.06},"wind_speed":{"units":"m/s","value":2.1},"lat":48.783333},{"temp":{"units":"C","value":2.53},"sunrise":{"value":"2020-11-29T06:53:16.516Z"},"observation_time":{"value":"2020-11-29T00:00:00.000Z"},"dewpoint":{"units":"C","value":1.47},"precipitation_type":{"value":"none"},"lon":9.183333,"surface_shortwave_radiation":{"units":"w/sqm","value":0},"wind_gust":{"units":"m/s","value":4.74},"precipitation":{"units":"mm/hr","value":0},"precipitation_probability":{"units":"%","value":0},"sunset":{"value":"2020-11-29T15:30:30.965Z"},"cloud_cover":{"units":"%","value":100},"humidity":{"units":"%","value":92},"wind_speed":{"units":"m/s","value":1.58},"lat":48.783333},{"temp":{"units":"C","value":2.58},"sunrise":{"value":"2020-11-29T06:53:16.516Z"},"observation_time":{"value":"2020-11-29T01:00:00.000Z"},"dewpoint":{"units":"C","value":1.47},"precipitation_type":{"value":"none"},"lon":9.183333,"surface_shortwave_radiation":{"units":"w/sqm","value":0},"wind_gust":{"units":"m/s","value":4.1},"precipitation":{"units":"mm/hr","value":0},"precipitation_probability":{"units":"%","value":0},"sunset":{"value":"2020-11-29T15:30:30.965Z"},"cloud_cover":{"units":"%","value":100},"humidity":{"units":"%","value":91.84},"wind_speed":{"units":"m/s","value":1.8},"lat":48.783333},{"temp":{"units":"C","value":2.62},"sunrise":{"value":"2020-11-29T06:53:16.516Z"},"observation_time":{"value":"2020-11-29T02:00:00.000Z"},"dewpoint":{"units":"C","value":0.69},"precipitation_type":{"value":"none"},"lon":9.183333,"surface_shortwave_radiation":{"units":"w/sqm","value":0},"wind_gust":{"units":"m/s","value":5.04},"precipitation":{"units":"mm/hr","value":0},"precipitation_probability":{"units":"%","value":0},"sunset":{"value":"2020-11-29T15:30:30.965Z"},"cloud_cover":{"units":"%","value":99.99},"humidity":{"units":"%","value":86.33},"wind_speed":{"units":"m/s","value":2.24},"lat":48.783333},{"temp":{"units":"C","value":2.38},"sunrise":{"value":"2020-11-29T06:53:16.516Z"},"observation_time":{"value":"2020-11-29T03:00:00.000Z"},"dewpoint":{"units":"C","value":-0.06},"precipitation_type":{"value":"none"},"lon":9.183333,"surface_shortwave_radiation":{"units":"w/sqm","value":0},"wind_gust":{"units":"m/s","value":5.71},"precipitation":{"units":"mm/hr","value":0},"precipitation_probability":{"units":"%","value":0},"sunset":{"value":"2020-11-29T15:30:30.965Z"},"cloud_cover":{"units":"%","value":100},"humidity":{"units":"%","value":83.12},"wind_speed":{"units":"m/s","value":2.57},"lat":48.783333},{"temp":{"units":"C","value":1.77},"sunrise":{"value":"2020-11-29T06:53:16.516Z"},"observation_time":{"value":"2020-11-29T04:00:00.000Z"},"dewpoint":{"units":"C","value":-0.37},"precipitation_type":{"value":"none"},"lon":9.183333,"surface_shortwave_radiation":{"units":"w/sqm","value":0},"wind_gust":{"units":"m/s","value":6.65},"precipitation":{"units":"mm/hr","value":0},"precipitation_probability":{"units":"%","value":0},"sunset":{"value":"2020-11-29T15:30:30.965Z"},"cloud_cover":{"units":"%","value":100},"humidity":{"units":"%","value":84.8},"wind_speed":{"units":"m/s","value":2.97},"lat":48.783333},{"temp":{"units":"C","value":1.27},"sunrise":{"value":"2020-11-29T06:53:16.516Z"},"observation_time":{"value":"2020-11-29T05:00:00.000Z"},"dewpoint":{"units":"C","value":-0.98},"precipitation_type":{"value":"none"},"lon":9.183333,"surface_shortwave_radiation":{"units":"w/sqm","value":0},"wind_gust":{"units":"m/s","value":7.07},"precipitation":{"units":"mm/hr","value":0},"precipitation_probability":{"units":"%","value":0},"sunset":{"value":"2020-11-29T15:30:30.965Z"},"cloud_cover":{"units":"%","value":100},"humidity":{"units":"%","value":84.09},"wind_speed":{"units":"m/s","value":3.15},"lat":48.783333},{"temp":{"units":"C","value":0.87},"sunrise":{"value":"2020-11-29T06:53:16.516Z"},"observation_time":{"value":"2020-11-29T06:00:00.000Z"},"dewpoint":{"units":"C","value":-2.52},"precipitation_type":{"value":"none"},"lon":9.183333,"surface_shortwave_radiation":{"units":"w/sqm","value":0},"wind_gust":{"units":"m/s","value":7.29},"precipitation":{"units":"mm/hr","value":0},"precipitation_probability":{"units":"%","value":0},"sunset":{"value":"2020-11-29T15:30:30.965Z"},"cloud_cover":{"units":"%","value":94.8},"humidity":{"units":"%","value":77.43},"wind_speed":{"units":"m/s","value":3.01},"lat":48.783333},{"temp":{"units":"C","value":0.56},"sunrise":{"value":"2020-11-29T06:53:16.516Z"},"observation_time":{"value":"2020-11-29T07:00:00.000Z"},"dewpoint":{"units":"C","value":-3.25},"precipitation_type":{"value":"none"},"lon":9.183333,"surface_shortwave_radiation":{"units":"w/sqm","value":0.01},"wind_gust":{"units":"m/s","value":6.77},"precipitation":{"units":"mm/hr","value":0},"precipitation_probability":{"units":"%","value":0},"sunset":{"value":"2020-11-29T15:30:30.965Z"},"cloud_cover":{"units":"%","value":74.5},"humidity":{"units":"%","value":73.88},"wind_speed":{"units":"m/s","value":2.4},"lat":48.783333},{"temp":{"units":"C","value":0.45},"sunrise":{"value":"2020-11-29T06:53:16.516Z"},"observation_time":{"value":"2020-11-29T08:00:00.000Z"},"dewpoint":{"units":"C","value":-3.04},"precipitation_type":{"value":"none"},"lon":9.183333,"surface_shortwave_radiation":{"units":"w/sqm","value":28.91},"wind_gust":{"units":"m/s","value":5.58},"precipitation":{"units":"mm/hr","value":0},"precipitation_probability":{"units":"%","value":0},"sunset":{"value":"2020-11-29T15:30:30.965Z"},"cloud_cover":{"units":"%","value":44.63},"humidity":{"units":"%","value":76.99},"wind_speed":{"units":"m/s","value":2.43},"lat":48.783333},{"temp":{"units":"C","value":1.07},"sunrise":{"value":"2020-11-29T06:53:16.516Z"},"observation_time":{"value":"2020-11-29T09:00:00.000Z"},"dewpoint":{"units":"C","value":-3.21},"precipitation_type":{"value":"none"},"lon":9.183333,"surface_shortwave_radiation":{"units":"w/sqm","value":85.08},"wind_gust":{"units":"m/s","value":7.66},"precipitation":{"units":"mm/hr","value":0},"precipitation_probability":{"units":"%","value":0},"sunset":{"value":"2020-11-29T15:30:30.965Z"},"cloud_cover":{"units":"%","value":59.5},"humidity":{"units":"%","value":72.74},"wind_speed":{"units":"m/s","value":3.35},"lat":48.783333},{"temp":{"units":"C","value":1.71},"sunrise":{"value":"2020-11-29T06:53:16.516Z"},"observation_time":{"value":"2020-11-29T10:00:00.000Z"},"dewpoint":{"units":"C","value":-3.66},"precipitation_type":{"value":"none"},"lon":9.183333,"surface_shortwave_radiation":{"units":"w/sqm","value":138.89},"wind_gust":{"units":"m/s","value":8.29},"precipitation":{"units":"mm/hr","value":0},"precipitation_probability":{"units":"%","value":0},"sunset":{"value":"2020-11-29T15:30:30.965Z"},"cloud_cover":{"units":"%","value":87.89},"humidity":{"units":"%","value":67.01},"wind_speed":{"units":"m/s","value":3.3},"lat":48.783333},{"temp":{"units":"C","value":2.46},"sunrise":{"value":"2020-11-29T06:53:16.516Z"},"observation_time":{"value":"2020-11-29T11:00:00.000Z"},"dewpoint":{"units":"C","value":-3.51},"precipitation_type":{"value":"none"},"lon":9.183333,"surface_shortwave_radiation":{"units":"w/sqm","value":168.33},"wind_gust":{"units":"m/s","value":7.67},"precipitation":{"units":"mm/hr","value":0},"precipitation_probability":{"units":"%","value":0},"sunset":{"value":"2020-11-29T15:30:30.965Z"},"cloud_cover":{"units":"%","value":39.18},"humidity":{"units":"%","value":64.22},"wind_speed":{"units":"m/s","value":2.85},"lat":48.783333},{"temp":{"units":"C","value":2.91},"sunrise":{"value":"2020-11-29T06:53:16.516Z"},"observation_time":{"value":"2020-11-29T12:00:00.000Z"},"dewpoint":{"units":"C","value":-3.32},"precipitation_type":{"value":"none"},"lon":9.183333,"surface_shortwave_radiation":{"units":"w/sqm","value":166.51},"wind_gust":{"units":"m/s","value":6.74},"precipitation":{"units":"mm/hr","value":0},"precipitation_probability":{"units":"%","value":0},"sunset":{"value":"2020-11-29T15:30:30.965Z"},"cloud_cover":{"units":"%","value":37.6},"humidity":{"units":"%","value":63.11},"wind_speed":{"units":"m/s","value":2.64},"lat":48.783333},{"temp":{"units":"C","value":3.09},"sunrise":{"value":"2020-11-29T06:53:16.516Z"},"observation_time":{"value":"2020-11-29T13:00:00.000Z"},"dewpoint":{"units":"C","value":-3.05},"precipitation_type":{"value":"none"},"lon":9.183333,"surface_shortwave_radiation":{"units":"w/sqm","value":139.14},"wind_gust":{"units":"m/s","value":6.31},"precipitation":{"units":"mm/hr","value":0},"precipitation_probability":{"units":"%","value":0},"sunset":{"value":"2020-11-29T15:30:30.965Z"},"cloud_cover":{"units":"%","value":35.18},"humidity":{"units":"%","value":63.58},"wind_speed":{"units":"m/s","value":2.55},"lat":48.783333},{"temp":{"units":"C","value":2.91},"sunrise":{"value":"2020-11-29T06:53:16.516Z"},"observation_time":{"value":"2020-11-29T14:00:00.000Z"},"dewpoint":{"units":"C","value":-3.03},"precipitation_type":{"value":"none"},"lon":9.183333,"surface_shortwave_radiation":{"units":"w/sqm","value":94.1},"wind_gust":{"units":"m/s","value":6.15},"precipitation":{"units":"mm/hr","value":0},"precipitation_probability":{"units":"%","value":0},"sunset":{"value":"2020-11-29T15:30:30.965Z"},"cloud_cover":{"units":"%","value":29.22},"humidity":{"units":"%","value":64.4},"wind_speed":{"units":"m/s","value":2.59},"lat":48.783333},{"temp":{"units":"C","value":2.29},"sunrise":{"value":"2020-11-29T06:53:16.516Z"},"observation_time":{"value":"2020-11-29T15:00:00.000Z"},"dewpoint":{"units":"C","value":-2.95},"precipitation_type":{"value":"none"},"lon":9.183333,"surface_shortwave_radiation":{"units":"w/sqm","value":44.39},"wind_gust":{"units":"m/s","value":5.99},"precipitation":{"units":"mm/hr","value":0},"precipitation_probability":{"units":"%","value":0},"sunset":{"value":"2020-11-29T15:30:30.965Z"},"cloud_cover":{"units":"%","value":14.96},"humidity":{"units":"%","value":67.32},"wind_speed":{"units":"m/s","value":1.98},"lat":48.783333},{"temp":{"units":"C","value":1.14},"sunrise":{"value":"2020-11-29T06:53:16.516Z"},"observation_time":{"value":"2020-11-29T16:00:00.000Z"},"dewpoint":{"units":"C","value":-2.7},"precipitation_type":{"value":"none"},"lon":9.183333,"surface_shortwave_radiation":{"units":"w/sqm","value":4.15},"wind_gust":{"units":"m/s","value":4.17},"precipitation":{"units":"mm/hr","value":0},"precipitation_probability":{"units":"%","value":0},"sunset":{"value":"2020-11-29T15:30:30.965Z"},"cloud_cover":{"units":"%","value":8.8},"humidity":{"units":"%","value":74.35},"wind_speed":{"units":"m/s","value":1.3},"lat":48.783333},{"temp":{"units":"C","value":0.41},"sunrise":{"value":"2020-11-29T06:53:16.516Z"},"observation_time":{"value":"2020-11-29T17:00:00.000Z"},"dewpoint":{"units":"C","value":-2.69},"precipitation_type":{"value":"none"},"lon":9.183333,"surface_shortwave_radiation":{"units":"w/sqm","value":0.03},"wind_gust":{"units":"m/s","value":2.6},"precipitation":{"units":"mm/hr","value":0},"precipitation_probability":{"units":"%","value":0},"sunset":{"value":"2020-11-29T15:30:30.965Z"},"cloud_cover":{"units":"%","value":4.52},"humidity":{"units":"%","value":78.86},"wind_speed":{"units":"m/s","value":0.97},"lat":48.783333},{"temp":{"units":"C","value":-0.1},"sunrise":{"value":"2020-11-29T06:53:16.516Z"},"observation_time":{"value":"2020-11-29T18:00:00.000Z"},"dewpoint":{"units":"C","value":-2.75},"precipitation_type":{"value":"none"},"lon":9.183333,"surface_shortwave_radiation":{"units":"w/sqm","value":0},"wind_gust":{"units":"m/s","value":1.93},"precipitation":{"units":"mm/hr","value":0},"precipitation_probability":{"units":"%","value":0},"sunset":{"value":"2020-11-29T15:30:30.965Z"},"cloud_cover":{"units":"%","value":5.33},"humidity":{"units":"%","value":80.84},"wind_speed":{"units":"m/s","value":0.87},"lat":48.783333},{"temp":{"units":"C","value":-0.53},"sunrise":{"value":"2020-11-29T06:53:16.516Z"},"observation_time":{"value":"2020-11-29T19:00:00.000Z"},"dewpoint":{"units":"C","value":-2.84},"precipitation_type":{"value":"none"},"lon":9.183333,"surface_shortwave_radiation":{"units":"w/sqm","value":0},"wind_gust":{"units":"m/s","value":1.49},"precipitation":{"units":"mm/hr","value":0},"precipitation_probability":{"units":"%","value":0},"sunset":{"value":"2020-11-29T15:30:30.965Z"},"cloud_cover":{"units":"%","value":0},"humidity":{"units":"%","value":82.26},"wind_speed":{"units":"m/s","value":0.72},"lat":48.783333},{"temp":{"units":"C","value":-0.98},"sunrise":{"value":"2020-11-29T06:53:16.516Z"},"observation_time":{"value":"2020-11-29T20:00:00.000Z"},"dewpoint":{"units":"C","value":-3.01},"precipitation_type":{"value":"none"},"lon":9.183333,"surface_shortwave_radiation":{"units":"w/sqm","value":0},"wind_gust":{"units":"m/s","value":1.11},"precipitation":{"units":"mm/hr","value":0},"precipitation_probability":{"units":"%","value":0},"sunset":{"value":"2020-11-29T15:30:30.965Z"},"cloud_cover":{"units":"%","value":0},"humidity":{"units":"%","value":84.27},"wind_speed":{"units":"m/s","value":0.63},"lat":48.783333},{"temp":{"units":"C","value":-1.35},"sunrise":{"value":"2020-11-29T06:53:16.516Z"},"observation_time":{"value":"2020-11-29T21:00:00.000Z"},"dewpoint":{"units":"C","value":-3.13},"precipitation_type":{"value":"none"},"lon":9.183333,"surface_shortwave_radiation":{"units":"w/sqm","value":0},"wind_gust":{"units":"m/s","value":0.92},"precipitation":{"units":"mm/hr","value":0},"precipitation_probability":{"units":"%","value":0},"sunset":{"value":"2020-11-29T15:30:30.965Z"},"cloud_cover":{"units":"%","value":0},"humidity":{"units":"%","value":85.92},"wind_speed":{"units":"m/s","value":0.3},"lat":48.783333},{"temp":{"units":"C","value":-1.7},"sunrise":{"value":"2020-11-29T06:53:16.516Z"},"observation_time":{"value":"2020-11-29T22:00:00.000Z"},"dewpoint":{"units":"C","value":-3.29},"precipitation_type":{"value":"none"},"lon":9.183333,"surface_shortwave_radiation":{"units":"w/sqm","value":0},"wind_gust":{"units":"m/s","value":0.79},"precipitation":{"units":"mm/hr","value":0},"precipitation_probability":{"units":"%","value":0},"sunset":{"value":"2020-11-29T15:30:30.965Z"},"cloud_cover":{"units":"%","value":0},"humidity":{"units":"%","value":87.25},"wind_speed":{"units":"m/s","value":0.34},"lat":48.783333},{"temp":{"units":"C","value":-1.87},"sunrise":{"value":"2020-11-29T06:53:16.516Z"},"observation_time":{"value":"2020-11-29T23:00:00.000Z"},"dewpoint":{"units":"C","value":-3.41},"precipitation_type":{"value":"none"},"lon":9.183333,"surface_shortwave_radiation":{"units":"w/sqm","value":0},"wind_gust":{"units":"m/s","value":0.62},"precipitation":{"units":"mm/hr","value":0},"precipitation_probability":{"units":"%","value":0},"sunset":{"value":"2020-11-29T15:30:30.965Z"},"cloud_cover":{"units":"%","value":1.06},"humidity":{"units":"%","value":87.47},"wind_speed":{"units":"m/s","value":0.08},"lat":48.783333},{"temp":{"units":"C","value":-2.2},"sunrise":{"value":"2020-11-30T06:54:34.932Z"},"observation_time":{"value":"2020-11-30T00:00:00.000Z"},"dewpoint":{"units":"C","value":-3.41},"precipitation_type":{"value":"none"},"lon":9.183333,"surface_shortwave_radiation":{"units":"w/sqm","value":0},"wind_gust":{"units":"m/s","value":0.87},"precipitation":{"units":"mm/hr","value":0},"precipitation_probability":{"units":"%","value":0},"sunset":{"value":"2020-11-30T15:29:56.997Z"},"cloud_cover":{"units":"%","value":8.07},"humidity":{"units":"%","value":90.07},"wind_speed":{"units":"m/s","value":0.58},"lat":48.783333},{"temp":{"units":"C","value":-2.72},"sunrise":{"value":"2020-11-30T06:54:34.932Z"},"observation_time":{"value":"2020-11-30T01:00:00.000Z"},"dewpoint":{"units":"C","value":-3.57},"precipitation_type":{"value":"none"},"lon":9.183333,"surface_shortwave_radiation":{"units":"w/sqm","value":0},"wind_gust":{"units":"m/s","value":1.03},"precipitation":{"units":"mm/hr","value":0},"precipitation_probability":{"units":"%","value":0},"sunset":{"value":"2020-11-30T15:29:56.997Z"},"cloud_cover":{"units":"%","value":10.22},"humidity":{"units":"%","value":92.94},"wind_speed":{"units":"m/s","value":0.52},"lat":48.783333},{"temp":{"units":"C","value":-3.18},"sunrise":{"value":"2020-11-30T06:54:34.932Z"},"observation_time":{"value":"2020-11-30T02:00:00.000Z"},"dewpoint":{"units":"C","value":-3.61},"precipitation_type":{"value":"none"},"lon":9.183333,"surface_shortwave_radiation":{"units":"w/sqm","value":0},"wind_gust":{"units":"m/s","value":1.58},"precipitation":{"units":"mm/hr","value":0},"precipitation_probability":{"units":"%","value":0},"sunset":{"value":"2020-11-30T15:29:56.997Z"},"cloud_cover":{"units":"%","value":10.29},"humidity":{"units":"%","value":95.46},"wind_speed":{"units":"m/s","value":0.62},"lat":48.783333},{"temp":{"units":"C","value":-3.57},"sunrise":{"value":"2020-11-30T06:54:34.932Z"},"observation_time":{"value":"2020-11-30T03:00:00.000Z"},"dewpoint":{"units":"C","value":-3.76},"precipitation_type":{"value":"none"},"lon":9.183333,"surface_shortwave_radiation":{"units":"w/sqm","value":0},"wind_gust":{"units":"m/s","value":1.44},"precipitation":{"units":"mm/hr","value":0},"precipitation_probability":{"units":"%","value":0},"sunset":{"value":"2020-11-30T15:29:56.997Z"},"cloud_cover":{"units":"%","value":24.58},"humidity":{"units":"%","value":96.73},"wind_speed":{"units":"m/s","value":0.37},"lat":48.783333},{"temp":{"units":"C","value":-4.36},"sunrise":{"value":"2020-11-30T06:54:34.932Z"},"observation_time":{"value":"2020-11-30T04:00:00.000Z"},"dewpoint":{"units":"C","value":-4.31},"precipitation_type":{"value":"none"},"lon":9.183333,"surface_shortwave_radiation":{"units":"w/sqm","value":0},"wind_gust":{"units":"m/s","value":1.54},"precipitation":{"units":"mm/hr","value":0},"precipitation_probability":{"units":"%","value":0},"sunset":{"value":"2020-11-30T15:29:56.997Z"},"cloud_cover":{"units":"%","value":85.91},"humidity":{"units":"%","value":98.62},"wind_speed":{"units":"m/s","value":0.61},"lat":48.783333},{"temp":{"units":"C","value":-5.08},"sunrise":{"value":"2020-11-30T06:54:34.932Z"},"observation_time":{"value":"2020-11-30T05:00:00.000Z"},"dewpoint":{"units":"C","value":-4.67},"precipitation_type":{"value":"none"},"lon":9.183333,"surface_shortwave_radiation":{"units":"w/sqm","value":0},"wind_gust":{"units":"m/s","value":1.72},"precipitation":{"units":"mm/hr","value":0},"precipitation_probability":{"units":"%","value":0},"sunset":{"value":"2020-11-30T15:29:56.997Z"},"cloud_cover":{"units":"%","value":97.5},"humidity":{"units":"%","value":100},"wind_speed":{"units":"m/s","value":0.54},"lat":48.783333},{"temp":{"units":"C","value":-5.78},"sunrise":{"value":"2020-11-30T06:54:34.932Z"},"observation_time":{"value":"2020-11-30T06:00:00.000Z"},"dewpoint":{"units":"C","value":-5.3},"precipitation_type":{"value":"none"},"lon":9.183333,"surface_shortwave_radiation":{"units":"w/sqm","value":0},"wind_gust":{"units":"m/s","value":1.7},"precipitation":{"units":"mm/hr","value":0},"precipitation_probability":{"units":"%","value":0},"sunset":{"value":"2020-11-30T15:29:56.997Z"},"cloud_cover":{"units":"%","value":100},"humidity":{"units":"%","value":100},"wind_speed":{"units":"m/s","value":0.6},"lat":48.783333},{"temp":{"units":"C","value":-6.19},"sunrise":{"value":"2020-11-30T06:54:34.932Z"},"observation_time":{"value":"2020-11-30T07:00:00.000Z"},"dewpoint":{"units":"C","value":-5.84},"precipitation_type":{"value":"none"},"lon":9.183333,"surface_shortwave_radiation":{"units":"w/sqm","value":0},"wind_gust":{"units":"m/s","value":2.24},"precipitation":{"units":"mm/hr","value":0},"precipitation_probability":{"units":"%","value":0},"sunset":{"value":"2020-11-30T15:29:56.997Z"},"cloud_cover":{"units":"%","value":100},"humidity":{"units":"%","value":100},"wind_speed":{"units":"m/s","value":0.63},"lat":48.783333},{"temp":{"units":"C","value":-6.38},"sunrise":{"value":"2020-11-30T06:54:34.932Z"},"observation_time":{"value":"2020-11-30T08:00:00.000Z"},"dewpoint":{"units":"C","value":-6.24},"precipitation_type":{"value":"none"},"lon":9.183333,"surface_shortwave_radiation":{"units":"w/sqm","value":25.21},"wind_gust":{"units":"m/s","value":2.07},"precipitation":{"units":"mm/hr","value":0},"precipitation_probability":{"units":"%","value":0},"sunset":{"value":"2020-11-30T15:29:56.997Z"},"cloud_cover":{"units":"%","value":100},"humidity":{"units":"%","value":99.85},"wind_speed":{"units":"m/s","value":0.56},"lat":48.783333},{"temp":{"units":"C","value":-5.41},"sunrise":{"value":"2020-11-30T06:54:34.932Z"},"observation_time":{"value":"2020-11-30T09:00:00.000Z"},"dewpoint":{"units":"C","value":-5.73},"precipitation_type":{"value":"none"},"lon":9.183333,"surface_shortwave_radiation":{"units":"w/sqm","value":85.68},"wind_gust":{"units":"m/s","value":2.38},"precipitation":{"units":"mm/hr","value":0},"precipitation_probability":{"units":"%","value":0},"sunset":{"value":"2020-11-30T15:29:56.997Z"},"cloud_cover":{"units":"%","value":93.98},"humidity":{"units":"%","value":97.1},"wind_speed":{"units":"m/s","value":0.77},"lat":48.783333},{"temp":{"units":"C","value":-3.53},"sunrise":{"value":"2020-11-30T06:54:34.932Z"},"observation_time":{"value":"2020-11-30T10:00:00.000Z"},"dewpoint":{"units":"C","value":-4.84},"precipitation_type":{"value":"none"},"lon":9.183333,"surface_shortwave_radiation":{"units":"w/sqm","value":138.01},"wind_gust":{"units":"m/s","value":2.39},"precipitation":{"units":"mm/hr","value":0},"precipitation_probability":{"units":"%","value":0},"sunset":{"value":"2020-11-30T15:29:56.997Z"},"cloud_cover":{"units":"%","value":54.65},"humidity":{"units":"%","value":89.91},"wind_speed":{"units":"m/s","value":0.53},"lat":48.783333},{"temp":{"units":"C","value":-2.09},"sunrise":{"value":"2020-11-30T06:54:34.932Z"},"observation_time":{"value":"2020-11-30T11:00:00.000Z"},"dewpoint":{"units":"C","value":-4.15},"precipitation_type":{"value":"none"},"lon":9.183333,"surface_shortwave_radiation":{"units":"w/sqm","value":167.12},"wind_gust":{"units":"m/s","value":2.26},"precipitation":{"units":"mm/hr","value":0},"precipitation_probability":{"units":"%","value":0},"sunset":{"value":"2020-11-30T15:29:56.997Z"},"cloud_cover":{"units":"%","value":41.05},"humidity":{"units":"%","value":82.72},"wind_speed":{"units":"m/s","value":0.72},"lat":48.783333},{"temp":{"units":"C","value":-0.65},"sunrise":{"value":"2020-11-30T06:54:34.932Z"},"observation_time":{"value":"2020-11-30T12:00:00.000Z"},"dewpoint":{"units":"C","value":-3.48},"precipitation_type":{"value":"none"},"lon":9.183333,"surface_shortwave_radiation":{"units":"w/sqm","value":161.99},"wind_gust":{"units":"m/s","value":2.88},"precipitation":{"units":"mm/hr","value":0},"precipitation_probability":{"units":"%","value":0},"sunset":{"value":"2020-11-30T15:29:56.997Z"},"cloud_cover":{"units":"%","value":3.96},"humidity":{"units":"%","value":78.36},"wind_speed":{"units":"m/s","value":0.71},"lat":48.783333},{"temp":{"units":"C","value":0.12},"sunrise":{"value":"2020-11-30T06:54:34.932Z"},"observation_time":{"value":"2020-11-30T13:00:00.000Z"},"dewpoint":{"units":"C","value":-3.11},"precipitation_type":{"value":"none"},"lon":9.183333,"surface_shortwave_radiation":{"units":"w/sqm","value":125.2},"wind_gust":{"units":"m/s","value":2.39},"precipitation":{"units":"mm/hr","value":0},"precipitation_probability":{"units":"%","value":0},"sunset":{"value":"2020-11-30T15:29:56.997Z"},"cloud_cover":{"units":"%","value":0},"humidity":{"units":"%","value":76.47},"wind_speed":{"units":"m/s","value":0.85},"lat":48.783333},{"temp":{"units":"C","value":0.22},"sunrise":{"value":"2020-11-30T06:54:34.932Z"},"observation_time":{"value":"2020-11-30T14:00:00.000Z"},"dewpoint":{"units":"C","value":-2.77},"precipitation_type":{"value":"none"},"lon":9.183333,"surface_shortwave_radiation":{"units":"w/sqm","value":83.71},"wind_gust":{"units":"m/s","value":2.23},"precipitation":{"units":"mm/hr","value":0},"precipitation_probability":{"units":"%","value":0},"sunset":{"value":"2020-11-30T15:29:56.997Z"},"cloud_cover":{"units":"%","value":0},"humidity":{"units":"%","value":77.87},"wind_speed":{"units":"m/s","value":0.71},"lat":48.783333},{"temp":{"units":"C","value":-0.43},"sunrise":{"value":"2020-11-30T06:54:34.932Z"},"observation_time":{"value":"2020-11-30T15:00:00.000Z"},"dewpoint":{"units":"C","value":-2.72},"precipitation_type":{"value":"none"},"lon":9.183333,"surface_shortwave_radiation":{"units":"w/sqm","value":41.18},"wind_gust":{"units":"m/s","value":2.15},"precipitation":{"units":"mm/hr","value":0},"precipitation_probability":{"units":"%","value":0},"sunset":{"value":"2020-11-30T15:29:56.997Z"},"cloud_cover":{"units":"%","value":0},"humidity":{"units":"%","value":83.86},"wind_speed":{"units":"m/s","value":0.78},"lat":48.783333},{"temp":{"units":"C","value":-1.37},"sunrise":{"value":"2020-11-30T06:54:34.932Z"},"observation_time":{"value":"2020-11-30T16:00:00.000Z"},"dewpoint":{"units":"C","value":-2.95},"precipitation_type":{"value":"none"},"lon":9.183333,"surface_shortwave_radiation":{"units":"w/sqm","value":3.85},"wind_gust":{"units":"m/s","value":2.18},"precipitation":{"units":"mm/hr","value":0},"precipitation_probability":{"units":"%","value":0},"sunset":{"value":"2020-11-30T15:29:56.997Z"},"cloud_cover":{"units":"%","value":0},"humidity":{"units":"%","value":88.34},"wind_speed":{"units":"m/s","value":0.33},"lat":48.783333},{"temp":{"units":"C","value":-1.96},"sunrise":{"value":"2020-11-30T06:54:34.932Z"},"observation_time":{"value":"2020-11-30T17:00:00.000Z"},"dewpoint":{"units":"C","value":-3.2},"precipitation_type":{"value":"none"},"lon":9.183333,"surface_shortwave_radiation":{"units":"w/sqm","value":0},"wind_gust":{"units":"m/s","value":1.74},"precipitation":{"units":"mm/hr","value":0},"precipitation_probability":{"units":"%","value":0},"sunset":{"value":"2020-11-30T15:29:56.997Z"},"cloud_cover":{"units":"%","value":0},"humidity":{"units":"%","value":90.5},"wind_speed":{"units":"m/s","value":0.77},"lat":48.783333},{"temp":{"units":"C","value":-2.52},"sunrise":{"value":"2020-11-30T06:54:34.932Z"},"observation_time":{"value":"2020-11-30T18:00:00.000Z"},"dewpoint":{"units":"C","value":-3.38},"precipitation_type":{"value":"none"},"lon":9.183333,"surface_shortwave_radiation":{"units":"w/sqm","value":0},"wind_gust":{"units":"m/s","value":1.64},"precipitation":{"units":"mm/hr","value":0},"precipitation_probability":{"units":"%","value":0},"sunset":{"value":"2020-11-30T15:29:56.997Z"},"cloud_cover":{"units":"%","value":0},"humidity":{"units":"%","value":92.41},"wind_speed":{"units":"m/s","value":0.2},"lat":48.783333},{"temp":{"units":"C","value":-2.83},"sunrise":{"value":"2020-11-30T06:54:34.932Z"},"observation_time":{"value":"2020-11-30T19:00:00.000Z"},"dewpoint":{"units":"C","value":-3.36},"precipitation_type":{"value":"none"},"lon":9.183333,"surface_shortwave_radiation":{"units":"w/sqm","value":0},"wind_gust":{"units":"m/s","value":1.35},"precipitation":{"units":"mm/hr","value":0},"precipitation_probability":{"units":"%","value":0},"sunset":{"value":"2020-11-30T15:29:56.997Z"},"cloud_cover":{"units":"%","value":0},"humidity":{"units":"%","value":93.39},"wind_speed":{"units":"m/s","value":0.59},"lat":48.783333},{"temp":{"units":"C","value":-3.18},"sunrise":{"value":"2020-11-30T06:54:34.932Z"},"observation_time":{"value":"2020-11-30T20:00:00.000Z"},"dewpoint":{"units":"C","value":-3.51},"precipitation_type":{"value":"none"},"lon":9.183333,"surface_shortwave_radiation":{"units":"w/sqm","value":0},"wind_gust":{"units":"m/s","value":1.61},"precipitation":{"units":"mm/hr","value":0},"precipitation_probability":{"units":"%","value":0},"sunset":{"value":"2020-11-30T15:29:56.997Z"},"cloud_cover":{"units":"%","value":4.43},"humidity":{"units":"%","value":94.61},"wind_speed":{"units":"m/s","value":0.7},"lat":48.783333},{"temp":{"units":"C","value":-3.69},"sunrise":{"value":"2020-11-30T06:54:34.932Z"},"observation_time":{"value":"2020-11-30T21:00:00.000Z"},"dewpoint":{"units":"C","value":-3.81},"precipitation_type":{"value":"none"},"lon":9.183333,"surface_shortwave_radiation":{"units":"w/sqm","value":0},"wind_gust":{"units":"m/s","value":1.82},"precipitation":{"units":"mm/hr","value":0},"precipitation_probability":{"units":"%","value":0},"sunset":{"value":"2020-11-30T15:29:56.997Z"},"cloud_cover":{"units":"%","value":29.56},"humidity":{"units":"%","value":96.78},"wind_speed":{"units":"m/s","value":0.37},"lat":48.783333},{"temp":{"units":"C","value":-4.18},"sunrise":{"value":"2020-11-30T06:54:34.932Z"},"observation_time":{"value":"2020-11-30T22:00:00.000Z"},"dewpoint":{"units":"C","value":-4.24},"precipitation_type":{"value":"none"},"lon":9.183333,"surface_shortwave_radiation":{"units":"w/sqm","value":0},"wind_gust":{"units":"m/s","value":2.75},"precipitation":{"units":"mm/hr","value":0},"precipitation_probability":{"units":"%","value":5},"sunset":{"value":"2020-11-30T15:29:56.997Z"},"cloud_cover":{"units":"%","value":100},"humidity":{"units":"%","value":97.71},"wind_speed":{"units":"m/s","value":0.96},"lat":48.783333},{"temp":{"units":"C","value":-4.21},"sunrise":{"value":"2020-11-30T06:54:34.932Z"},"observation_time":{"value":"2020-11-30T23:00:00.000Z"},"dewpoint":{"units":"C","value":-4.55},"precipitation_type":{"value":"none"},"lon":9.183333,"surface_shortwave_radiation":{"units":"w/sqm","value":0},"wind_gust":{"units":"m/s","value":2.91},"precipitation":{"units":"mm/hr","value":0},"precipitation_probability":{"units":"%","value":10},"sunset":{"value":"2020-11-30T15:29:56.997Z"},"cloud_cover":{"units":"%","value":100},"humidity":{"units":"%","value":98.65},"wind_speed":{"units":"m/s","value":0.93},"lat":48.783333},{"temp":{"units":"C","value":-3.53},"sunrise":{"value":"2020-12-01T06:55:51.785Z"},"observation_time":{"value":"2020-12-01T00:00:00.000Z"},"dewpoint":{"units":"C","value":-4.38},"precipitation_type":{"value":"none"},"lon":9.183333,"surface_shortwave_radiation":{"units":"w/sqm","value":0},"wind_gust":{"units":"m/s","value":2.46},"precipitation":{"units":"mm/hr","value":0},"precipitation_probability":{"units":"%","value":15},"sunset":{"value":"2020-12-01T15:29:25.860Z"},"cloud_cover":{"units":"%","value":99.88},"humidity":{"units":"%","value":93.45},"wind_speed":{"units":"m/s","value":0.63},"lat":48.783333},{"temp":{"units":"C","value":-3.26},"sunrise":{"value":"2020-12-01T06:55:51.785Z"},"observation_time":{"value":"2020-12-01T01:00:00.000Z"},"dewpoint":{"units":"C","value":-4.32},"precipitation_type":{"value":"none"},"lon":9.183333,"surface_shortwave_radiation":{"units":"w/sqm","value":0},"wind_gust":{"units":"m/s","value":3.38},"precipitation":{"units":"mm/hr","value":0},"precipitation_probability":{"units":"%","value":25},"sunset":{"value":"2020-12-01T15:29:25.860Z"},"cloud_cover":{"units":"%","value":100},"humidity":{"units":"%","value":92.92},"wind_speed":{"units":"m/s","value":1.21},"lat":48.783333},{"temp":{"units":"C","value":-2.93},"sunrise":{"value":"2020-12-01T06:55:51.785Z"},"observation_time":{"value":"2020-12-01T02:00:00.000Z"},"dewpoint":{"units":"C","value":-3.96},"precipitation_type":{"value":"snow"},"lon":9.183333,"surface_shortwave_radiation":{"units":"w/sqm","value":0},"wind_gust":{"units":"m/s","value":2.87},"precipitation":{"units":"mm/hr","value":0.4277},"precipitation_probability":{"units":"%","value":40},"sunset":{"value":"2020-12-01T15:29:25.860Z"},"cloud_cover":{"units":"%","value":100},"humidity":{"units":"%","value":92.98},"wind_speed":{"units":"m/s","value":0.6},"lat":48.783333},{"temp":{"units":"C","value":-2.26},"sunrise":{"value":"2020-12-01T06:55:51.785Z"},"observation_time":{"value":"2020-12-01T03:00:00.000Z"},"dewpoint":{"units":"C","value":-2.92},"precipitation_type":{"value":"snow"},"lon":9.183333,"surface_shortwave_radiation":{"units":"w/sqm","value":0},"wind_gust":{"units":"m/s","value":3.54},"precipitation":{"units":"mm/hr","value":0.8262},"precipitation_probability":{"units":"%","value":50},"sunset":{"value":"2020-12-01T15:29:25.860Z"},"cloud_cover":{"units":"%","value":100},"humidity":{"units":"%","value":94.71},"wind_speed":{"units":"m/s","value":1.54},"lat":48.783333},{"temp":{"units":"C","value":-1.55},"sunrise":{"value":"2020-12-01T06:55:51.785Z"},"observation_time":{"value":"2020-12-01T04:00:00.000Z"},"dewpoint":{"units":"C","value":-2.15},"precipitation_type":{"value":"snow"},"lon":9.183333,"surface_shortwave_radiation":{"units":"w/sqm","value":0},"wind_gust":{"units":"m/s","value":3.64},"precipitation":{"units":"mm/hr","value":0.2246},"precipitation_probability":{"units":"%","value":55},"sunset":{"value":"2020-12-01T15:29:25.860Z"},"cloud_cover":{"units":"%","value":98.82},"humidity":{"units":"%","value":94.44},"wind_speed":{"units":"m/s","value":1.12},"lat":48.783333},{"temp":{"units":"C","value":-1.23},"sunrise":{"value":"2020-12-01T06:55:51.785Z"},"observation_time":{"value":"2020-12-01T05:00:00.000Z"},"dewpoint":{"units":"C","value":-1.7},"precipitation_type":{"value":"snow"},"lon":9.183333,"surface_shortwave_radiation":{"units":"w/sqm","value":0},"wind_gust":{"units":"m/s","value":2.54},"precipitation":{"units":"mm/hr","value":0.4133},"precipitation_probability":{"units":"%","value":65},"sunset":{"value":"2020-12-01T15:29:25.860Z"},"cloud_cover":{"units":"%","value":100},"humidity":{"units":"%","value":95.46},"wind_speed":{"units":"m/s","value":1.01},"lat":48.783333},{"temp":{"units":"C","value":-0.92},"sunrise":{"value":"2020-12-01T06:55:51.785Z"},"observation_time":{"value":"2020-12-01T06:00:00.000Z"},"dewpoint":{"units":"C","value":-1.28},"precipitation_type":{"value":"snow"},"lon":9.183333,"surface_shortwave_radiation":{"units":"w/sqm","value":0},"wind_gust":{"units":"m/s","value":2.47},"precipitation":{"units":"mm/hr","value":0.8652},"precipitation_probability":{"units":"%","value":75},"sunset":{"value":"2020-12-01T15:29:25.860Z"},"cloud_cover":{"units":"%","value":98},"humidity":{"units":"%","value":96.84},"wind_speed":{"units":"m/s","value":1.03},"lat":48.783333},{"temp":{"units":"C","value":-0.82},"sunrise":{"value":"2020-12-01T06:55:51.785Z"},"observation_time":{"value":"2020-12-01T07:00:00.000Z"},"dewpoint":{"units":"C","value":-1.21},"precipitation_type":{"value":"snow"},"lon":9.183333,"surface_shortwave_radiation":{"units":"w/sqm","value":0},"wind_gust":{"units":"m/s","value":2.3},"precipitation":{"units":"mm/hr","value":0.4863},"precipitation_probability":{"units":"%","value":75},"sunset":{"value":"2020-12-01T15:29:25.860Z"},"cloud_cover":{"units":"%","value":100},"humidity":{"units":"%","value":97.22},"wind_speed":{"units":"m/s","value":0.99},"lat":48.783333},{"temp":{"units":"C","value":-0.4},"sunrise":{"value":"2020-12-01T06:55:51.785Z"},"observation_time":{"value":"2020-12-01T08:00:00.000Z"},"dewpoint":{"units":"C","value":-0.61},"precipitation_type":{"value":"snow"},"lon":9.183333,"surface_shortwave_radiation":{"units":"w/sqm","value":7.35},"wind_gust":{"units":"m/s","value":2.19},"precipitation":{"units":"mm/hr","value":0.8286},"precipitation_probability":{"units":"%","value":70},"sunset":{"value":"2020-12-01T15:29:25.860Z"},"cloud_cover":{"units":"%","value":100},"humidity":{"units":"%","value":97.98},"wind_speed":{"units":"m/s","value":0.97},"lat":48.783333},{"temp":{"units":"C","value":-0.06},"sunrise":{"value":"2020-12-01T06:55:51.785Z"},"observation_time":{"value":"2020-12-01T09:00:00.000Z"},"dewpoint":{"units":"C","value":-0.31},"precipitation_type":{"value":"snow"},"lon":9.183333,"surface_shortwave_radiation":{"units":"w/sqm","value":25.3},"wind_gust":{"units":"m/s","value":2.13},"precipitation":{"units":"mm/hr","value":0.7966},"precipitation_probability":{"units":"%","value":65},"sunset":{"value":"2020-12-01T15:29:25.860Z"},"cloud_cover":{"units":"%","value":100},"humidity":{"units":"%","value":98.05},"wind_speed":{"units":"m/s","value":0.74},"lat":48.783333},{"temp":{"units":"C","value":0.19},"sunrise":{"value":"2020-12-01T06:55:51.785Z"},"observation_time":{"value":"2020-12-01T10:00:00.000Z"},"dewpoint":{"units":"C","value":-0.22},"precipitation_type":{"value":"snow"},"lon":9.183333,"surface_shortwave_radiation":{"units":"w/sqm","value":46.63},"wind_gust":{"units":"m/s","value":1.51},"precipitation":{"units":"mm/hr","value":0.3135},"precipitation_probability":{"units":"%","value":55},"sunset":{"value":"2020-12-01T15:29:25.860Z"},"cloud_cover":{"units":"%","value":99.9},"humidity":{"units":"%","value":96.54},"wind_speed":{"units":"m/s","value":0.39},"lat":48.783333},{"temp":{"units":"C","value":0.38},"sunrise":{"value":"2020-12-01T06:55:51.785Z"},"observation_time":{"value":"2020-12-01T11:00:00.000Z"},"dewpoint":{"units":"C","value":-0.08},"precipitation_type":{"value":"freezing rain"},"lon":9.183333,"surface_shortwave_radiation":{"units":"w/sqm","value":52.08},"wind_gust":{"units":"m/s","value":1.65},"precipitation":{"units":"mm/hr","value":0.1309},"precipitation_probability":{"units":"%","value":55},"sunset":{"value":"2020-12-01T15:29:25.860Z"},"cloud_cover":{"units":"%","value":100},"humidity":{"units":"%","value":97.62},"wind_speed":{"units":"m/s","value":0.72},"lat":48.783333},{"temp":{"units":"C","value":1.19},"sunrise":{"value":"2020-12-01T06:55:51.785Z"},"observation_time":{"value":"2020-12-01T12:00:00.000Z"},"dewpoint":{"units":"C","value":0.21},"precipitation_type":{"value":"none"},"lon":9.183333,"surface_shortwave_radiation":{"units":"w/sqm","value":77.41},"wind_gust":{"units":"m/s","value":1.8},"precipitation":{"units":"mm/hr","value":0},"precipitation_probability":{"units":"%","value":45},"sunset":{"value":"2020-12-01T15:29:25.860Z"},"cloud_cover":{"units":"%","value":100},"humidity":{"units":"%","value":93.45},"wind_speed":{"units":"m/s","value":0.33},"lat":48.783333},{"temp":{"units":"C","value":1.54},"sunrise":{"value":"2020-12-01T06:55:51.785Z"},"observation_time":{"value":"2020-12-01T13:00:00.000Z"},"dewpoint":{"units":"C","value":0.16},"precipitation_type":{"value":"snow"},"lon":9.183333,"surface_shortwave_radiation":{"units":"w/sqm","value":69.79},"wind_gust":{"units":"m/s","value":4.35},"precipitation":{"units":"mm/hr","value":0.0234},"precipitation_probability":{"units":"%","value":35},"sunset":{"value":"2020-12-01T15:29:25.860Z"},"cloud_cover":{"units":"%","value":97.61},"humidity":{"units":"%","value":88.84},"wind_speed":{"units":"m/s","value":1.83},"lat":48.783333},{"temp":{"units":"C","value":0.94},"sunrise":{"value":"2020-12-01T06:55:51.785Z"},"observation_time":{"value":"2020-12-01T14:00:00.000Z"},"dewpoint":{"units":"C","value":0.34},"precipitation_type":{"value":"freezing rain"},"lon":9.183333,"surface_shortwave_radiation":{"units":"w/sqm","value":45.8},"wind_gust":{"units":"m/s","value":5.13},"precipitation":{"units":"mm/hr","value":0.6289},"precipitation_probability":{"units":"%","value":30},"sunset":{"value":"2020-12-01T15:29:25.860Z"},"cloud_cover":{"units":"%","value":98.77},"humidity":{"units":"%","value":95.82},"wind_speed":{"units":"m/s","value":1.21},"lat":48.783333},{"temp":{"units":"C","value":0.91},"sunrise":{"value":"2020-12-01T06:55:51.785Z"},"observation_time":{"value":"2020-12-01T15:00:00.000Z"},"dewpoint":{"units":"C","value":0.32},"precipitation_type":{"value":"snow"},"lon":9.183333,"surface_shortwave_radiation":{"units":"w/sqm","value":21.15},"wind_gust":{"units":"m/s","value":3.55},"precipitation":{"units":"mm/hr","value":0.5508},"precipitation_probability":{"units":"%","value":30},"sunset":{"value":"2020-12-01T15:29:25.860Z"},"cloud_cover":{"units":"%","value":95.97},"humidity":{"units":"%","value":94.37},"wind_speed":{"units":"m/s","value":0.55},"lat":48.783333},{"temp":{"units":"C","value":0.84},"sunrise":{"value":"2020-12-01T06:55:51.785Z"},"observation_time":{"value":"2020-12-01T16:00:00.000Z"},"dewpoint":{"units":"C","value":0.24},"precipitation_type":{"value":"freezing rain"},"lon":9.183333,"surface_shortwave_radiation":{"units":"w/sqm","value":1.38},"wind_gust":{"units":"m/s","value":1.84},"precipitation":{"units":"mm/hr","value":0.3711},"precipitation_probability":{"units":"%","value":30},"sunset":{"value":"2020-12-01T15:29:25.860Z"},"cloud_cover":{"units":"%","value":96.02},"humidity":{"units":"%","value":94.67},"wind_speed":{"units":"m/s","value":0.51},"lat":48.783333},{"temp":{"units":"C","value":0.76},"sunrise":{"value":"2020-12-01T06:55:51.785Z"},"observation_time":{"value":"2020-12-01T17:00:00.000Z"},"dewpoint":{"units":"C","value":0.22},"precipitation_type":{"value":"snow"},"lon":9.183333,"surface_shortwave_radiation":{"units":"w/sqm","value":0},"wind_gust":{"units":"m/s","value":1.39},"precipitation":{"units":"mm/hr","value":0.3945},"precipitation_probability":{"units":"%","value":30},"sunset":{"value":"2020-12-01T15:29:25.860Z"},"cloud_cover":{"units":"%","value":97.44},"humidity":{"units":"%","value":94.51},"wind_speed":{"units":"m/s","value":0.47},"lat":48.783333},{"temp":{"units":"C","value":0.94},"sunrise":{"value":"2020-12-01T06:55:51.785Z"},"observation_time":{"value":"2020-12-01T18:00:00.000Z"},"dewpoint":{"units":"C","value":0.47},"precipitation_type":{"value":"snow"},"lon":9.183333,"surface_shortwave_radiation":{"units":"w/sqm","value":0},"wind_gust":{"units":"m/s","value":0.91},"precipitation":{"units":"mm/hr","value":0.7876},"precipitation_probability":{"units":"%","value":25},"sunset":{"value":"2020-12-01T15:29:25.860Z"},"cloud_cover":{"units":"%","value":99.8},"humidity":{"units":"%","value":94.27},"wind_speed":{"units":"m/s","value":0.48},"lat":48.783333},{"temp":{"units":"C","value":0.94},"sunrise":{"value":"2020-12-01T06:55:51.785Z"},"observation_time":{"value":"2020-12-01T19:00:00.000Z"},"dewpoint":{"units":"C","value":0.47},"precipitation_type":{"value":"snow"},"lon":9.183333,"surface_shortwave_radiation":{"units":"w/sqm","value":0},"wind_gust":{"units":"m/s","value":0.91},"precipitation":{"units":"mm/hr","value":0.7876},"precipitation_probability":{"units":"%","value":25},"sunset":{"value":"2020-12-01T15:29:25.860Z"},"cloud_cover":{"units":"%","value":99.8},"humidity":{"units":"%","value":94.27},"wind_speed":{"units":"m/s","value":0.48},"lat":48.783333},{"temp":{"units":"C","value":0.94},"sunrise":{"value":"2020-12-01T06:55:51.785Z"},"observation_time":{"value":"2020-12-01T20:00:00.000Z"},"dewpoint":{"units":"C","value":0.47},"precipitation_type":{"value":"snow"},"lon":9.183333,"surface_shortwave_radiation":{"units":"w/sqm","value":0},"wind_gust":{"units":"m/s","value":0.91},"precipitation":{"units":"mm/hr","value":0.7876},"precipitation_probability":{"units":"%","value":25},"sunset":{"value":"2020-12-01T15:29:25.860Z"},"cloud_cover":{"units":"%","value":99.8},"humidity":{"units":"%","value":94.27},"wind_speed":{"units":"m/s","value":0.48},"lat":48.783333},{"temp":{"units":"C","value":0.8},"sunrise":{"value":"2020-12-01T06:55:51.785Z"},"observation_time":{"value":"2020-12-01T21:00:00.000Z"},"dewpoint":{"units":"C","value":0.39},"precipitation_type":{"value":"snow"},"lon":9.183333,"surface_shortwave_radiation":{"units":"w/sqm","value":0},"wind_gust":{"units":"m/s","value":0.83},"precipitation":{"units":"mm/hr","value":0.7168},"precipitation_probability":{"units":"%","value":40},"sunset":{"value":"2020-12-01T15:29:25.860Z"},"cloud_cover":{"units":"%","value":91.84},"humidity":{"units":"%","value":94.57},"wind_speed":{"units":"m/s","value":0.47},"lat":48.783333},{"temp":{"units":"C","value":0.8},"sunrise":{"value":"2020-12-01T06:55:51.785Z"},"observation_time":{"value":"2020-12-01T22:00:00.000Z"},"dewpoint":{"units":"C","value":0.39},"precipitation_type":{"value":"snow"},"lon":9.183333,"surface_shortwave_radiation":{"units":"w/sqm","value":0},"wind_gust":{"units":"m/s","value":0.83},"precipitation":{"units":"mm/hr","value":0.7168},"precipitation_probability":{"units":"%","value":40},"sunset":{"value":"2020-12-01T15:29:25.860Z"},"cloud_cover":{"units":"%","value":91.84},"humidity":{"units":"%","value":94.57},"wind_speed":{"units":"m/s","value":0.47},"lat":48.783333},{"temp":{"units":"C","value":0.8},"sunrise":{"value":"2020-12-01T06:55:51.785Z"},"observation_time":{"value":"2020-12-01T23:00:00.000Z"},"dewpoint":{"units":"C","value":0.39},"precipitation_type":{"value":"snow"},"lon":9.183333,"surface_shortwave_radiation":{"units":"w/sqm","value":0},"wind_gust":{"units":"m/s","value":0.83},"precipitation":{"units":"mm/hr","value":0.7168},"precipitation_probability":{"units":"%","value":40},"sunset":{"value":"2020-12-01T15:29:25.860Z"},"cloud_cover":{"units":"%","value":91.84},"humidity":{"units":"%","value":94.57},"wind_speed":{"units":"m/s","value":0.47},"lat":48.783333},{"temp":{"units":"C","value":0.77},"sunrise":{"value":"2020-12-02T06:57:06.996Z"},"observation_time":{"value":"2020-12-02T00:00:00.000Z"},"dewpoint":{"units":"C","value":0.21},"precipitation_type":{"value":"snow"},"lon":9.183333,"surface_shortwave_radiation":{"units":"w/sqm","value":0},"wind_gust":{"units":"m/s","value":1.51},"precipitation":{"units":"mm/hr","value":0.1602},"precipitation_probability":{"units":"%","value":25},"sunset":{"value":"2020-12-02T15:28:57.587Z"},"cloud_cover":{"units":"%","value":96.18},"humidity":{"units":"%","value":95.66},"wind_speed":{"units":"m/s","value":0.65},"lat":48.783333},{"temp":{"units":"C","value":0.77},"sunrise":{"value":"2020-12-02T06:57:06.996Z"},"observation_time":{"value":"2020-12-02T01:00:00.000Z"},"dewpoint":{"units":"C","value":0.21},"precipitation_type":{"value":"snow"},"lon":9.183333,"surface_shortwave_radiation":{"units":"w/sqm","value":0},"wind_gust":{"units":"m/s","value":1.51},"precipitation":{"units":"mm/hr","value":0.1602},"precipitation_probability":{"units":"%","value":25},"sunset":{"value":"2020-12-02T15:28:57.587Z"},"cloud_cover":{"units":"%","value":96.18},"humidity":{"units":"%","value":95.66},"wind_speed":{"units":"m/s","value":0.65},"lat":48.783333},{"temp":{"units":"C","value":0.77},"sunrise":{"value":"2020-12-02T06:57:06.996Z"},"observation_time":{"value":"2020-12-02T02:00:00.000Z"},"dewpoint":{"units":"C","value":0.21},"precipitation_type":{"value":"snow"},"lon":9.183333,"surface_shortwave_radiation":{"units":"w/sqm","value":0},"wind_gust":{"units":"m/s","value":1.51},"precipitation":{"units":"mm/hr","value":0.1602},"precipitation_probability":{"units":"%","value":25},"sunset":{"value":"2020-12-02T15:28:57.587Z"},"cloud_cover":{"units":"%","value":96.18},"humidity":{"units":"%","value":95.66},"wind_speed":{"units":"m/s","value":0.65},"lat":48.783333},{"temp":{"units":"C","value":0.29},"sunrise":{"value":"2020-12-02T06:57:06.996Z"},"observation_time":{"value":"2020-12-02T03:00:00.000Z"},"dewpoint":{"units":"C","value":0.01},"precipitation_type":{"value":"snow"},"lon":9.183333,"surface_shortwave_radiation":{"units":"w/sqm","value":0},"wind_gust":{"units":"m/s","value":1.76},"precipitation":{"units":"mm/hr","value":0.0352},"precipitation_probability":{"units":"%","value":10},"sunset":{"value":"2020-12-02T15:28:57.587Z"},"cloud_cover":{"units":"%","value":100},"humidity":{"units":"%","value":96.81},"wind_speed":{"units":"m/s","value":0.64},"lat":48.783333},{"temp":{"units":"C","value":0.29},"sunrise":{"value":"2020-12-02T06:57:06.996Z"},"observation_time":{"value":"2020-12-02T04:00:00.000Z"},"dewpoint":{"units":"C","value":0.01},"precipitation_type":{"value":"snow"},"lon":9.183333,"surface_shortwave_radiation":{"units":"w/sqm","value":0},"wind_gust":{"units":"m/s","value":1.76},"precipitation":{"units":"mm/hr","value":0.0352},"precipitation_probability":{"units":"%","value":10},"sunset":{"value":"2020-12-02T15:28:57.587Z"},"cloud_cover":{"units":"%","value":100},"humidity":{"units":"%","value":96.81},"wind_speed":{"units":"m/s","value":0.64},"lat":48.783333},{"temp":{"units":"C","value":0.29},"sunrise":{"value":"2020-12-02T06:57:06.996Z"},"observation_time":{"value":"2020-12-02T05:00:00.000Z"},"dewpoint":{"units":"C","value":0.01},"precipitation_type":{"value":"snow"},"lon":9.183333,"surface_shortwave_radiation":{"units":"w/sqm","value":0},"wind_gust":{"units":"m/s","value":1.76},"precipitation":{"units":"mm/hr","value":0.0352},"precipitation_probability":{"units":"%","value":10},"sunset":{"value":"2020-12-02T15:28:57.587Z"},"cloud_cover":{"units":"%","value":100},"humidity":{"units":"%","value":96.81},"wind_speed":{"units":"m/s","value":0.64},"lat":48.783333},{"temp":{"units":"C","value":0.55},"sunrise":{"value":"2020-12-02T06:57:06.996Z"},"observation_time":{"value":"2020-12-02T06:00:00.000Z"},"dewpoint":{"units":"C","value":0.15},"precipitation_type":{"value":"snow"},"lon":9.183333,"surface_shortwave_radiation":{"units":"w/sqm","value":0},"wind_gust":{"units":"m/s","value":1.46},"precipitation":{"units":"mm/hr","value":0.0273},"precipitation_probability":{"units":"%","value":0},"sunset":{"value":"2020-12-02T15:28:57.587Z"},"cloud_cover":{"units":"%","value":98.39},"humidity":{"units":"%","value":96.7},"wind_speed":{"units":"m/s","value":0.76},"lat":48.783333},{"temp":{"units":"C","value":0.55},"sunrise":{"value":"2020-12-02T06:57:06.996Z"},"observation_time":{"value":"2020-12-02T07:00:00.000Z"},"dewpoint":{"units":"C","value":0.15},"precipitation_type":{"value":"snow"},"lon":9.183333,"surface_shortwave_radiation":{"units":"w/sqm","value":0},"wind_gust":{"units":"m/s","value":1.46},"precipitation":{"units":"mm/hr","value":0.0273},"precipitation_probability":{"units":"%","value":0},"sunset":{"value":"2020-12-02T15:28:57.587Z"},"cloud_cover":{"units":"%","value":98.39},"humidity":{"units":"%","value":96.7},"wind_speed":{"units":"m/s","value":0.76},"lat":48.783333},{"temp":{"units":"C","value":0.55},"sunrise":{"value":"2020-12-02T06:57:06.996Z"},"observation_time":{"value":"2020-12-02T08:00:00.000Z"},"dewpoint":{"units":"C","value":0.15},"precipitation_type":{"value":"snow"},"lon":9.183333,"surface_shortwave_radiation":{"units":"w/sqm","value":0},"wind_gust":{"units":"m/s","value":1.46},"precipitation":{"units":"mm/hr","value":0.0273},"precipitation_probability":{"units":"%","value":0},"sunset":{"value":"2020-12-02T15:28:57.587Z"},"cloud_cover":{"units":"%","value":98.39},"humidity":{"units":"%","value":96.7},"wind_speed":{"units":"m/s","value":0.76},"lat":48.783333},{"temp":{"units":"C","value":1.05},"sunrise":{"value":"2020-12-02T06:57:06.996Z"},"observation_time":{"value":"2020-12-02T09:00:00.000Z"},"dewpoint":{"units":"C","value":0.69},"precipitation_type":{"value":"snow"},"lon":9.183333,"surface_shortwave_radiation":{"units":"w/sqm","value":19.3},"wind_gust":{"units":"m/s","value":0.51},"precipitation":{"units":"mm/hr","value":0.0156},"precipitation_probability":{"units":"%","value":0},"sunset":{"value":"2020-12-02T15:28:57.587Z"},"cloud_cover":{"units":"%","value":95.88},"humidity":{"units":"%","value":97.92},"wind_speed":{"units":"m/s","value":0.07},"lat":48.783333},{"temp":{"units":"C","value":1.05},"sunrise":{"value":"2020-12-02T06:57:06.996Z"},"observation_time":{"value":"2020-12-02T10:00:00.000Z"},"dewpoint":{"units":"C","value":0.69},"precipitation_type":{"value":"snow"},"lon":9.183333,"surface_shortwave_radiation":{"units":"w/sqm","value":19.3},"wind_gust":{"units":"m/s","value":0.51},"precipitation":{"units":"mm/hr","value":0.0156},"precipitation_probability":{"units":"%","value":0},"sunset":{"value":"2020-12-02T15:28:57.587Z"},"cloud_cover":{"units":"%","value":95.88},"humidity":{"units":"%","value":97.92},"wind_speed":{"units":"m/s","value":0.07},"lat":48.783333},{"temp":{"units":"C","value":1.05},"sunrise":{"value":"2020-12-02T06:57:06.996Z"},"observation_time":{"value":"2020-12-02T11:00:00.000Z"},"dewpoint":{"units":"C","value":0.69},"precipitation_type":{"value":"snow"},"lon":9.183333,"surface_shortwave_radiation":{"units":"w/sqm","value":19.3},"wind_gust":{"units":"m/s","value":0.51},"precipitation":{"units":"mm/hr","value":0.0156},"precipitation_probability":{"units":"%","value":0},"sunset":{"value":"2020-12-02T15:28:57.587Z"},"cloud_cover":{"units":"%","value":95.88},"humidity":{"units":"%","value":97.92},"wind_speed":{"units":"m/s","value":0.07},"lat":48.783333},{"temp":{"units":"C","value":2.79},"sunrise":{"value":"2020-12-02T06:57:06.996Z"},"observation_time":{"value":"2020-12-02T12:00:00.000Z"},"dewpoint":{"units":"C","value":1.02},"precipitation_type":{"value":"snow"},"lon":9.183333,"surface_shortwave_radiation":{"units":"w/sqm","value":99.73},"wind_gust":{"units":"m/s","value":2.08},"precipitation":{"units":"mm/hr","value":0.0117},"precipitation_probability":{"units":"%","value":0},"sunset":{"value":"2020-12-02T15:28:57.587Z"},"cloud_cover":{"units":"%","value":100},"humidity":{"units":"%","value":88.05},"wind_speed":{"units":"m/s","value":0.78},"lat":48.783333},{"temp":{"units":"C","value":2.79},"sunrise":{"value":"2020-12-02T06:57:06.996Z"},"observation_time":{"value":"2020-12-02T13:00:00.000Z"},"dewpoint":{"units":"C","value":1.02},"precipitation_type":{"value":"snow"},"lon":9.183333,"surface_shortwave_radiation":{"units":"w/sqm","value":99.73},"wind_gust":{"units":"m/s","value":2.08},"precipitation":{"units":"mm/hr","value":0.0117},"precipitation_probability":{"units":"%","value":0},"sunset":{"value":"2020-12-02T15:28:57.587Z"},"cloud_cover":{"units":"%","value":100},"humidity":{"units":"%","value":88.05},"wind_speed":{"units":"m/s","value":0.78},"lat":48.783333},{"temp":{"units":"C","value":2.79},"sunrise":{"value":"2020-12-02T06:57:06.996Z"},"observation_time":{"value":"2020-12-02T14:00:00.000Z"},"dewpoint":{"units":"C","value":1.02},"precipitation_type":{"value":"snow"},"lon":9.183333,"surface_shortwave_radiation":{"units":"w/sqm","value":99.73},"wind_gust":{"units":"m/s","value":2.08},"precipitation":{"units":"mm/hr","value":0.0117},"precipitation_probability":{"units":"%","value":0},"sunset":{"value":"2020-12-02T15:28:57.587Z"},"cloud_cover":{"units":"%","value":100},"humidity":{"units":"%","value":88.05},"wind_speed":{"units":"m/s","value":0.78},"lat":48.783333},{"temp":{"units":"C","value":2.42},"sunrise":{"value":"2020-12-02T06:57:06.996Z"},"observation_time":{"value":"2020-12-02T15:00:00.000Z"},"dewpoint":{"units":"C","value":0.62},"precipitation_type":{"value":"none"},"lon":9.183333,"surface_shortwave_radiation":{"units":"w/sqm","value":64.28},"wind_gust":{"units":"m/s","value":2.6},"precipitation":{"units":"mm/hr","value":0},"precipitation_probability":{"units":"%","value":0},"sunset":{"value":"2020-12-02T15:28:57.587Z"},"cloud_cover":{"units":"%","value":86.66},"humidity":{"units":"%","value":87.35},"wind_speed":{"units":"m/s","value":0.95},"lat":48.783333},{"temp":{"units":"C","value":2.42},"sunrise":{"value":"2020-12-02T06:57:06.996Z"},"observation_time":{"value":"2020-12-02T16:00:00.000Z"},"dewpoint":{"units":"C","value":0.62},"precipitation_type":{"value":"none"},"lon":9.183333,"surface_shortwave_radiation":{"units":"w/sqm","value":64.28},"wind_gust":{"units":"m/s","value":2.6},"precipitation":{"units":"mm/hr","value":0},"precipitation_probability":{"units":"%","value":0},"sunset":{"value":"2020-12-02T15:28:57.587Z"},"cloud_cover":{"units":"%","value":86.66},"humidity":{"units":"%","value":87.35},"wind_speed":{"units":"m/s","value":0.95},"lat":48.783333},{"temp":{"units":"C","value":2.42},"sunrise":{"value":"2020-12-02T06:57:06.996Z"},"observation_time":{"value":"2020-12-02T17:00:00.000Z"},"dewpoint":{"units":"C","value":0.62},"precipitation_type":{"value":"none"},"lon":9.183333,"surface_shortwave_radiation":{"units":"w/sqm","value":64.28},"wind_gust":{"units":"m/s","value":2.6},"precipitation":{"units":"mm/hr","value":0},"precipitation_probability":{"units":"%","value":0},"sunset":{"value":"2020-12-02T15:28:57.587Z"},"cloud_cover":{"units":"%","value":86.66},"humidity":{"units":"%","value":87.35},"wind_speed":{"units":"m/s","value":0.95},"lat":48.783333},{"temp":{"units":"C","value":0.9},"sunrise":{"value":"2020-12-02T06:57:06.996Z"},"observation_time":{"value":"2020-12-02T18:00:00.000Z"},"dewpoint":{"units":"C","value":-0.07},"precipitation_type":{"value":"none"},"lon":9.183333,"surface_shortwave_radiation":{"units":"w/sqm","value":0},"wind_gust":{"units":"m/s","value":1.29},"precipitation":{"units":"mm/hr","value":0},"precipitation_probability":{"units":"%","value":0},"sunset":{"value":"2020-12-02T15:28:57.587Z"},"cloud_cover":{"units":"%","value":74.18},"humidity":{"units":"%","value":93.37},"wind_speed":{"units":"m/s","value":0.76},"lat":48.783333},{"temp":{"units":"C","value":0.9},"sunrise":{"value":"2020-12-02T06:57:06.996Z"},"observation_time":{"value":"2020-12-02T19:00:00.000Z"},"dewpoint":{"units":"C","value":-0.07},"precipitation_type":{"value":"none"},"lon":9.183333,"surface_shortwave_radiation":{"units":"w/sqm","value":0},"wind_gust":{"units":"m/s","value":1.29},"precipitation":{"units":"mm/hr","value":0},"precipitation_probability":{"units":"%","value":0},"sunset":{"value":"2020-12-02T15:28:57.587Z"},"cloud_cover":{"units":"%","value":74.18},"humidity":{"units":"%","value":93.37},"wind_speed":{"units":"m/s","value":0.76},"lat":48.783333},{"temp":{"units":"C","value":0.9},"sunrise":{"value":"2020-12-02T06:57:06.996Z"},"observation_time":{"value":"2020-12-02T20:00:00.000Z"},"dewpoint":{"units":"C","value":-0.07},"precipitation_type":{"value":"none"},"lon":9.183333,"surface_shortwave_radiation":{"units":"w/sqm","value":0},"wind_gust":{"units":"m/s","value":1.29},"precipitation":{"units":"mm/hr","value":0},"precipitation_probability":{"units":"%","value":0},"sunset":{"value":"2020-12-02T15:28:57.587Z"},"cloud_cover":{"units":"%","value":74.18},"humidity":{"units":"%","value":93.37},"wind_speed":{"units":"m/s","value":0.76},"lat":48.783333},{"temp":{"units":"C","value":0.85},"sunrise":{"value":"2020-12-02T06:57:06.996Z"},"observation_time":{"value":"2020-12-02T21:00:00.000Z"},"dewpoint":{"units":"C","value":-0.66},"precipitation_type":{"value":"none"},"lon":9.183333,"surface_shortwave_radiation":{"units":"w/sqm","value":0},"wind_gust":{"units":"m/s","value":1.06},"precipitation":{"units":"mm/hr","value":0},"precipitation_probability":{"units":"%","value":0},"sunset":{"value":"2020-12-02T15:28:57.587Z"},"cloud_cover":{"units":"%","value":96.1},"humidity":{"units":"%","value":88.19},"wind_speed":{"units":"m/s","value":0.2},"lat":48.783333},{"temp":{"units":"C","value":0.85},"sunrise":{"value":"2020-12-02T06:57:06.996Z"},"observation_time":{"value":"2020-12-02T22:00:00.000Z"},"dewpoint":{"units":"C","value":-0.66},"precipitation_type":{"value":"none"},"lon":9.183333,"surface_shortwave_radiation":{"units":"w/sqm","value":0},"wind_gust":{"units":"m/s","value":1.06},"precipitation":{"units":"mm/hr","value":0},"precipitation_probability":{"units":"%","value":0},"sunset":{"value":"2020-12-02T15:28:57.587Z"},"cloud_cover":{"units":"%","value":96.1},"humidity":{"units":"%","value":88.19},"wind_speed":{"units":"m/s","value":0.2},"lat":48.783333},{"temp":{"units":"C","value":0.85},"sunrise":{"value":"2020-12-02T06:57:06.996Z"},"observation_time":{"value":"2020-12-02T23:00:00.000Z"},"dewpoint":{"units":"C","value":-0.66},"precipitation_type":{"value":"none"},"lon":9.183333,"surface_shortwave_radiation":{"units":"w/sqm","value":0},"wind_gust":{"units":"m/s","value":1.06},"precipitation":{"units":"mm/hr","value":0},"precipitation_probability":{"units":"%","value":0},"sunset":{"value":"2020-12-02T15:28:57.587Z"},"cloud_cover":{"units":"%","value":96.1},"humidity":{"units":"%","value":88.19},"wind_speed":{"units":"m/s","value":0.2},"lat":48.783333},{"temp":{"units":"C","value":0.06},"sunrise":{"value":"2020-12-03T06:58:20.491Z"},"observation_time":{"value":"2020-12-03T00:00:00.000Z"},"dewpoint":{"units":"C","value":-0.48},"precipitation_type":{"value":"none"},"lon":9.183333,"surface_shortwave_radiation":{"units":"w/sqm","value":0},"wind_gust":{"units":"m/s","value":1.84},"precipitation":{"units":"mm/hr","value":0},"precipitation_probability":{"units":"%","value":0},"sunset":{"value":"2020-12-03T15:28:32.204Z"},"cloud_cover":{"units":"%","value":90.59},"humidity":{"units":"%","value":93.4},"wind_speed":{"units":"m/s","value":0.84},"lat":48.783333},{"temp":{"units":"C","value":0.06},"sunrise":{"value":"2020-12-03T06:58:20.491Z"},"observation_time":{"value":"2020-12-03T01:00:00.000Z"},"dewpoint":{"units":"C","value":-0.48},"precipitation_type":{"value":"none"},"lon":9.183333,"surface_shortwave_radiation":{"units":"w/sqm","value":0},"wind_gust":{"units":"m/s","value":1.84},"precipitation":{"units":"mm/hr","value":0},"precipitation_probability":{"units":"%","value":0},"sunset":{"value":"2020-12-03T15:28:32.204Z"},"cloud_cover":{"units":"%","value":90.59},"humidity":{"units":"%","value":93.4},"wind_speed":{"units":"m/s","value":0.84},"lat":48.783333},{"temp":{"units":"C","value":0.06},"sunrise":{"value":"2020-12-03T06:58:20.491Z"},"observation_time":{"value":"2020-12-03T02:00:00.000Z"},"dewpoint":{"units":"C","value":-0.48},"precipitation_type":{"value":"none"},"lon":9.183333,"surface_shortwave_radiation":{"units":"w/sqm","value":0},"wind_gust":{"units":"m/s","value":1.84},"precipitation":{"units":"mm/hr","value":0},"precipitation_probability":{"units":"%","value":0},"sunset":{"value":"2020-12-03T15:28:32.204Z"},"cloud_cover":{"units":"%","value":90.59},"humidity":{"units":"%","value":93.4},"wind_speed":{"units":"m/s","value":0.84},"lat":48.783333},{"temp":{"units":"C","value":-1.65},"sunrise":{"value":"2020-12-03T06:58:20.491Z"},"observation_time":{"value":"2020-12-03T03:00:00.000Z"},"dewpoint":{"units":"C","value":-1.87},"precipitation_type":{"value":"none"},"lon":9.183333,"surface_shortwave_radiation":{"units":"w/sqm","value":0},"wind_gust":{"units":"m/s","value":3.11},"precipitation":{"units":"mm/hr","value":0},"precipitation_probability":{"units":"%","value":0},"sunset":{"value":"2020-12-03T15:28:32.204Z"},"cloud_cover":{"units":"%","value":100},"humidity":{"units":"%","value":97.68},"wind_speed":{"units":"m/s","value":1.14},"lat":48.783333},{"temp":{"units":"C","value":-1.65},"sunrise":{"value":"2020-12-03T06:58:20.491Z"},"observation_time":{"value":"2020-12-03T04:00:00.000Z"},"dewpoint":{"units":"C","value":-1.87},"precipitation_type":{"value":"none"},"lon":9.183333,"surface_shortwave_radiation":{"units":"w/sqm","value":0},"wind_gust":{"units":"m/s","value":3.11},"precipitation":{"units":"mm/hr","value":0},"precipitation_probability":{"units":"%","value":0},"sunset":{"value":"2020-12-03T15:28:32.204Z"},"cloud_cover":{"units":"%","value":100},"humidity":{"units":"%","value":97.68},"wind_speed":{"units":"m/s","value":1.14},"lat":48.783333},{"temp":{"units":"C","value":-1.65},"sunrise":{"value":"2020-12-03T06:58:20.491Z"},"observation_time":{"value":"2020-12-03T05:00:00.000Z"},"dewpoint":{"units":"C","value":-1.87},"precipitation_type":{"value":"none"},"lon":9.183333,"surface_shortwave_radiation":{"units":"w/sqm","value":0},"wind_gust":{"units":"m/s","value":3.11},"precipitation":{"units":"mm/hr","value":0},"precipitation_probability":{"units":"%","value":0},"sunset":{"value":"2020-12-03T15:28:32.204Z"},"cloud_cover":{"units":"%","value":100},"humidity":{"units":"%","value":97.68},"wind_speed":{"units":"m/s","value":1.14},"lat":48.783333},{"temp":{"units":"C","value":-1.65},"sunrise":{"value":"2020-12-03T06:58:20.491Z"},"observation_time":{"value":"2020-12-03T06:00:00.000Z"},"dewpoint":{"units":"C","value":-1.87},"precipitation_type":{"value":"none"},"lon":9.183333,"surface_shortwave_radiation":{"units":"w/sqm","value":0},"wind_gust":{"units":"m/s","value":3.11},"precipitation":{"units":"mm/hr","value":0},"precipitation_probability":{"units":"%","value":0},"sunset":{"value":"2020-12-03T15:28:32.204Z"},"cloud_cover":{"units":"%","value":100},"humidity":{"units":"%","value":97.68},"wind_speed":{"units":"m/s","value":1.14},"lat":48.783333},{"temp":{"units":"C","value":-2.34},"sunrise":{"value":"2020-12-03T06:58:20.491Z"},"observation_time":{"value":"2020-12-03T07:00:00.000Z"},"dewpoint":{"units":"C","value":-2.77},"precipitation_type":{"value":"none"},"lon":9.183333,"surface_shortwave_radiation":{"units":"w/sqm","value":0.02},"wind_gust":{"units":"m/s","value":2.69},"precipitation":{"units":"mm/hr","value":0},"precipitation_probability":{"units":"%","value":0},"sunset":{"value":"2020-12-03T15:28:32.204Z"},"cloud_cover":{"units":"%","value":64.62},"humidity":{"units":"%","value":95.86},"wind_speed":{"units":"m/s","value":1.1},"lat":48.783333}]